Workbook
Name IG_CTRL: '[2]IG Def (7.1)'!$A:$A
Name IG_CTRL: #REF!

Sheet License
A1: License
A2: Please see our terms of use here: https://www.cisecurity.org/cis-securesuite/cis-securesuite-membership-terms-of-use/

Sheet Level 1
A1: Section # | B1: Recommendation # | C1: Title | D1: Assessment Status | E1: Description | F1: Rationale Statement | G1: Impact Statement | H1: Remediation Procedure | I1: Audit Procedure | J1: Additional Information | K1: CIS Controls | L1: CIS Safeguards 1 (v8) | M1: CIS Safeguards 2 (v8) | N1: CIS Safeguards 3 (v8) | O1: v8 IG1 | P1: v8 IG2 | Q1: v8 IG3 | R1: CIS Safeguards 1 (v7) | S1: CIS Safeguards 2 (v7) | T1: CIS Safeguards 3 (v7) | U1: v7 IG1 | V1: v7 IG2 | W1: v7 IG3 | X1: References | Y1: Default Value
A2: 1 | C2: Introduction | E2: This introduction section and the subsections herein provide informative articles which instruct on the use of the CIS Foundations and Service Category Benchmarks. No recommendations will be found in this section, just articles of relevant information. Please carefully review the articles in this introductory section and orient yourself with our structured approach to Benchmarking for Cloud Service Providers (CSPs). This approach differs from other CIS Benchmarks because: - there are too many different products/services in CSP product directories to practically cover in any one Benchmark, - architectural and design decisions will affect the scope and relevance of recommendations, and - there are a variety of methods for interfacing with CSP products and services. **Cloud Benchmarks - A Two-Step Approach to Securing Your Cloud Environments:** - **Step 1:** Start with Foundations Benchmarks. Apply as many recommendations as **practical** for your environment; "100%" 'compliance' is not always possible. Not all Foundations Benchmark recommendations can be applied at the same time, and not all recommendations will be relevant to your environment. Use the recommendation Profile Levels and your understanding of your unique environment architecture to determine which recommendations are in scope. - **Step 2:** Use the Service Category Benchmarks for service-specific defense-in-depth recommendations. Apply recommendations only for the services **IN USE** in your environment. Use the recommendation Profile Levels, and your understanding of your unique environment architecture to determine which recommendations are in scope.
A3: 1.1 | C3: CIS Microsoft Azure Foundations Benchmarks | E3: The suggested approach for securing your Microsoft Azure cloud environment is to start with the **latest version** of the CIS Microsoft Azure Foundations Benchmark. Because CSP environments are constantly changing, previous versions of the Foundations Benchmarks should not be used. Previous releases may contain incorrect product names, outdated procedures, deprecated features, and other inaccuracies. The CIS Foundations Benchmark provides prescriptive guidance for configuring a subset of Microsoft Azure Services with an emphasis on foundational, testable, and architecture agnostic settings for services. The Microsoft Azure Foundations Benchmark is what you should start with when beginning to secure your Azure environment. It is also the foundation for which all other Azure Service Category Benchmarks are built on so that as you grow your cloud presence and usage of the services offered you have the necessary guidance to securely configure your environment as it fits with your company’s policy. All CIS Benchmarks are created and maintained through consensus-based collaboration. Should you have feedback, suggested changes, or just like to get involved in the continued maintenance and development of CIS Microsoft Azure Benchmarks, please register on CIS WorkBench at https://workbench.cisecurity.org and join the CIS Microsoft Azure Benchmarks Community.
A4: 1.2 | C4: CIS Microsoft Azure Service Category Benchmarks | E4: After configuring your environment with the CIS Microsoft Azure Foundations Benchmark, we suggest pursuing defense-in-depth and service-specific recommendations for your Azure Services by reviewing the Service Category Benchmarks. The Service Category Benchmarks are being produced with the vision that recommendations for all security-relevant products/services offered by a CSP should have a 'home,' but the Foundations Benchmarks should retain the most crucial recommendations and not be made vast, intimidating, and impractical. The Service Category Benchmark recommendations should be applied **ONLY** for the CSP products and services that are actively **IN USE** in your environment. In each Service Category Benchmark, you may find that your environment uses none, or only a couple services from a list of many. Please review the services employed in your environment carefully to accurately scope the recommendations you apply. Failure to apply only the recommendations you need may introduce vulnerabilities, technical debt, and unnecessary expenses. Using the Microsoft Azure Product Directory (https://azure.microsoft.com/en-us/products/) as a source of categorical grouping of these services, our vision is to produce a full set of CIS Microsoft Azure Service Category Benchmarks to cover all security-relevant services. A list of planned and published Service Category Benchmarks for the Azure Community can be found on the community dashboard here: https://workbench.cisecurity.org/communities/72. **Your help is needed to bring this vision to life!** Please consider joining our CIS Microsoft Azure Community to contribute your expertise and knowledge in securing products and services from the Microsoft Azure product family. All CIS Benchmarks are created and maintained through consensus-based collaboration. Should you have feedback, suggested changes, or just like to get involved in the continued maintenance and development of CIS Microsoft Azure Benchmarks, please register on CIS WorkBench at https://workbench.cisecurity.org and join the CIS Microsoft Azure Benchmarks community.
A5: 1.3 | C5: Multiple Methods of Audit and Remediation | E5: Throughout the Benchmark, Audit and Remediation procedures are prescribed using up to five different methods. These multiple methods are presented for the convenience of readers who will be coming from different technical and experiential backgrounds. To perform any given Audit or Remediation, only one method needs to be performed. Not every method is available for every recommendation, and many that are available are not yet written for every recommendation. The methods presented in the Benchmark are formatted and titled as follows: - "**From Azure Portal**" - This is the administrative GUI accessed at https://portal.azure.com. - "**From Azure CLI**" - See additional detail in the next section. - "**From PowerShell**" - See additional detail in the next section. - "**From REST API**" - An Application Programming Interface (API) for HTTP operations on service endpoints. - "**From Azure Policy**" - Azure Policy provides an object-based method of evaluating configuration states and other governance detail. Information for the purpose of automating Azure Policy evaluation can be found in the "Automating with Azure Policy" section below. **Setting Up PowerShell and Azure CLI** In order to use the Azure Command Line Interface (CLI) and the Azure PowerShell methods for audit and remediation procedures, the following permissions are required for the account running the procedures: 1. Global Reader 2. Security Reader 3. Subscription Contributor 4. Key Vault Get/List privileges on Keys, Secrets, Certificates, and Certificate Authorities 5. Network allow listing for any source IP address performing the audit activities 6. Permissions to use PowerShell and Azure CLI These permissions can be directly assigned or assigned via Privileged Identity Management. The Azure CLI tool can be installed from the following location: https://docs.microsoft.com/en-us/cli/azure/install-azure-cli-windows?tabs=azure-cli For PowerShell, the following cmdlets are required: 1. Azure PowerShell: https://docs.microsoft.com/en-us/powershell/azure/install-az-ps-msi?view=azps-12.2.0 1. Microsoft Graph PowerShell: https://learn.microsoft.com/en-us/powershell/microsoftgraph/installation?view=graph-powershell-1.0 **Authenticating with Azure CLI** Run the following command from either PowerShell or command prompt: ``` az login --tenant <tenant id> --subscription <subscription ID> ``` **Authenticating with PowerShell** Login to the Azure tenant and subscription using the following command: ``` Connect-AzAccount ``` If you receive a message indicating `InteractiveBrowserCredential authentication failed`, disable web account manager (WAM) to force a browser authentication with the following command: ``` Update-AzConfig -EnableLoginByWam $false ``` Then attempt using 'Connect-AzAccount' again. If the browser-based login is not available, you may need to use device-code authentication, but this should be avoided and is not recommended because it is a persistent authentication method and specifically blocked by recommendations found in the Azure Benchmarks. Instructions for this method will not be provided as it is not recommended. For the Graph PowerShell module, the log in method is the same. ``` Connect-MgGraph ```
A6: 1.4 | C6: Automating with Azure Policy | E6: Azure Policy provides built-in objects ("Policy Definitions") and a platform for "Policy as Code" that can be used to evaluate and/or enforce configuration states for individual resources or groups of resources. Where a relevant Azure Policy Definition or multiple Policy Definitions have been identified as applicable to a recommendation in this Benchmark, the Policy ID(s) and associated Policy Name will be listed in the "From Azure Policy" method header. Interfacing with Azure Policy can be performed through the Azure Portal, Azure CLI, Azure PowerShell, REST API, Azure Resource Manager, Bicep, Terraform, or using GitHub Actions. Azure Policy Definitions can be batched together and structured using an "Initiative Definition" (aka: "Initiative" or "Compliance Initiative" or "Policy Set") which is constructed in a JSON file. Scoping and filtering an Azure Policy Initiative is necessary to ensure that the query is relevant to the architecture and requirements of an organization. Microsoft provides some pre-built Initiative Definitions as a starting point intended to assist in achieving governance and compliance objectives - from Security Frameworks to CIS Benchmarks. These pre-built Initiative Definitions provide a structured set of Policy Definitions with additional metadata to evaluate resource states and configurations, then present the results in an easily readable format. While the Initiatives are a very valuable starting point, they will likely require additional attention for your specific environment, so it is a valuable investment in time to understand how to interact with them to create, remove, update, and delete policy definitions and modify enforcement effects. With some effort and care, policies within an initiative which start by default in an "audit" or "auditIfNotExists" effect can be matured into enforcement effects of "deny," "modify," or "deployIfNotExists" but each individual Policy Definition should be well understood before modifying the effect. In environments that have an advanced posture and custom policy needs, custom Policy Definitions can be created for specialized resource evaluations. Building an Initiative Definition that fits the needs of your organization is generally a great way to improve overall security posture and has the potential to bring and keep your organization closer to compliance and best practice standards. **NOTE On Outdated Policy Initiatives of CIS Benchmarks:** CIS is aware that outdated versions of the CIS Benchmark are made available through the built-in Policy Initiatives offered in Azure. We always recommend using only the **latest available version** of the CIS Microsoft Azure Foundations Benchmark at all times and **using the latest published version of this Benchmark to update and maintain the policy initiative in your environments**. Cloud service provider environments are in a constant state of change, so best practice guidance - including Azure Policy recommendations - is also in a constant state of reconsideration and possible change. **General references for Azure Policy:** - Microsoft Learn - General Azure Policy Documentation: https://learn.microsoft.com/en-us/azure/governance/policy/ - Designing Policy as Code workflows: https://learn.microsoft.com/en-us/azure/governance/policy/concepts/policy-as-code - Retrieving Azure Policy information: https://learn.microsoft.com/en-us/azure/governance/policy/how-to/get-compliance-data - AzPolicyAdvertizer - a very well curated database of Azure Policy Definitions, Initiatives, and related material: https://www.azadvertizer.net/azpolicyadvertizer_all.html **Azure Policy GUI** - The Azure Policy GUI interface can be found in the Azure Admin Portal - simply search for `Policy` and select the Policy service. **Azure Policy from Azure CLI** - Azure CLI commands: https://learn.microsoft.com/en-us/cli/azure/policy?view=azure-cli-latest **Azure Policy from PowerShell** - PowerShell commands: https://learn.microsoft.com/en-us/powershell/module/az.resources#policy **Azure Policy from REST API** - REST API reference: https://learn.microsoft.com/en-us/rest/api/policy/ **Azure Policy from GitHub Actions** - Azure Policy GitHub Actions: https://github.com/marketplace/actions/azure-policy-compliance-scan **Azure Policy from Terraform** - Provider: azurerm - Reference: https://registry.terraform.io/providers/hashicorp/azurerm/latest/docs/resources/policy_definition
A7: 2 | C7: Analytics Services | E7: To better understand the relationship between the Foundations Benchmark and Services Benchmarks, please read the "Introduction" section of this document. Azure Product Directory Reference: https://azure.microsoft.com/en-us/products#analytics **FEEDBACK REQUEST:** Is there a specific service or recommendation in this section that you'd like to see addressed or improved? Let us know by making a ticket or starting a discussion in the CIS Microsoft Azure Community (https://workbench.cisecurity.org/communities/72).
A8: 2.1 | C8: Azure Databricks
A9: 2.1 | B9: 2.1.1 | C9: Ensure that Azure Databricks is deployed in a customer-managed virtual network (VNet) | D9: Automated | E9: Networking for Azure Databricks can be set up in a few different ways. Using a customer-managed Virtual Network (VNet) (also known as VNet Injection) ensures that compute clusters and control planes are securely isolated within the organization’s network boundary. By default, Databricks creates a managed VNet, which provides limited control over network security policies, firewall configurations, and routing. | F9: Using a customer-managed VNet ensures better control over network security and aligns with zero-trust architecture principles. It allows for: - Restricted outbound internet access to prevent unauthorized data exfiltration. - Integration with on-premises networks via VPN or ExpressRoute for hybrid connectivity. - Fine-grained NSG policies to restrict access at the subnet level. - Private Link for secure API access, avoiding public internet exposure. | G9: '- Requires additional configuration during Databricks workspace deployment. - Might increase operational overhead for network maintenance. - May impact connectivity if misconfigured (e.g., restrictive NSG rules or missing routes). | H9: **Remediate from Azure Portal** 1. Delete the existing Databricks workspace (migration required). 1. Create a new Databricks workspace with VNet Injection: 1. Go to Azure Portal → Create Databricks Workspace. 1. Select Advanced Networking. 1. Choose Deploy into your own Virtual Network. 1. Specify a customer-managed VNet and associated subnets. 1. Enable Private Link for secure API access. **Remediate from Azure CLI** Deploy a new Databricks workspace in a custom VNet: ``` az databricks workspace create --name <databricks-workspace-name> \ --resource-group <resource-group-name> \ --location <region> \ --managed-resource-group <managed-rg-name> \ --enable-no-public-ip true \ --network-security-group-rule "NoAzureServices" \ --public-network-access Disabled \ --custom-virtual-network-id /subscriptions/<subscription-id>/resourceGroups/<resource-group-name>/providers/Microsoft.Network/virtualNetworks/<vnet-name> ``` Ensure NSG Rules are correctly configured: ``` az network nsg rule create --resource-group <resource-group-name> \ --nsg-name <nsg-name> \ --name "DenyAllOutbound" \ --direction Outbound \ --access Deny \ --priority 4096 ``` **Remediate from PowerShell** ``` New-AzDatabricksWorkspace -ResourceGroupName <resource-group-name> -Name <databricks-workspace-name> -Location <region> -ManagedResourceGroupName <managed-rg-name> -CustomVirtualNetworkId "/subscriptions/<subscription-id>/resourceGroups/<resource-group-name>/providers/Microsoft.Network/virtualNetworks/<vnet-name>" ``` | I9: **Audit from Azure Portal** 1. Go to Azure Portal → Search for Databricks Workspaces. 1. Select the Databricks Workspace to audit. 1. Under Networking, check if the workspace is deployed in a Customer-Managed VNet. 1. If the Virtual Network field shows Databricks-Managed VNet, it is non-compliant. 1. Verify NSG rules and Private Endpoints for fine-grained access control. **Audit from Azure CLI** Run the following command to check if Databricks is using a customer-managed VNet: ``` az network vnet show --resource-group <resource-group-name> --name <vnet-name> ``` Ensure that Databricks subnets are present in the VNet configuration. Validate NSG rules attached to the Databricks subnets. **Audit from PowerShell** ``` Get-AzDatabricksWorkspace -ResourceGroupName <resource-group-name> -Name <databricks-workspace-name> | Select-Object VirtualNetworkId ``` If VirtualNetworkId is null or shows a Databricks-Managed VNet, it is non-compliant. **Audit from Azure Policy** If referencing a digital copy of this Benchmark, clicking a Policy ID will open a link to the associated Policy definition in Azure. If referencing a printed copy, you can search Policy IDs from this URL: https://portal.azure.com/#view/Microsoft_Azure_Policy/PolicyMenuBlade/~/Definitions - **Policy ID:** [9c25c9e4-ee12-4882-afd2-11fb9d87893f](https://portal.azure.com/#view/Microsoft_Azure_Policy/PolicyDetailBlade/definitionId/%2Fproviders%2FMicrosoft.Authorization%2FpolicyDefinitions%2F9c25c9e4-ee12-4882-afd2-11fb9d87893f) **- Name:** 'Azure Databricks Workspaces should be in a virtual network' | K9: TITLE:Establish and Maintain a Secure Network Architecture CONTROL:v8 12.2 DESCRIPTION:Establish and maintain a secure network architecture. A secure network architecture must address segmentation, least privilege, and availability, at a minimum.;TITLE:Segment the Network Based on Sensitivity CONTROL:v7 14.1 DESCRIPTION:Segment the network based on the label or classification level of the information stored on the servers, locate all sensitive information on separated Virtual Local Area Networks (VLANs).; | L9: 12.2 | P9: X | Q9: X | R9: 14.1 | V9: X | W9: X | Y9: By default, Azure Databricks uses a Databricks-Managed VNet.
A10: 2.1 | B10: 2.1.2 | C10: Ensure that network security groups are configured for Databricks subnets | D10: Automated | E10: Network Security Groups (NSGs) should be implemented to control inbound and outbound traffic to Azure Databricks subnets, ensuring only authorized communication. NSGs operate using a rule-based model that includes both explicit allow/deny rules and an implicit deny at the end of the rule list. This means that any traffic not explicitly allowed is automatically denied. To ensure secure and predictable behavior, NSGs should be configured with explicit deny rules for known unwanted traffic, in addition to the default implicit deny, to improve visibility and auditability of blocked traffic. This approach helps enforce least privilege and minimizes the risk of unauthorized access to Databricks resources. | F10: Using NSGs with both explicit allow and deny rules provides clear documentation and control over permitted and prohibited traffic. While Azure NSGs implicitly deny all traffic not explicitly allowed, defining explicit deny rules for known malicious or unnecessary sources enhances clarity, simplifies troubleshooting, and supports compliance audits. This layered approach strengthens the security posture of Databricks environments by ensuring only essential communication is permitted. | G10: '- NSGs require ongoing maintenance to ensure rule accuracy and alignment with evolving business and security requirements. - Misconfigured NSGs—especially overly broad allow rules or missing explicit denies—can inadvertently expose Databricks resources or block legitimate traffic. - Relying solely on implicit deny may obscure the intent behind traffic restrictions, making it harder to audit or troubleshoot network behavior. | H10: **Remediate from Azure Portal** 1. Assign NSG to Databricks subnets under Networking > NSG Settings. | I10: **Audit from Azure Portal** 1. Navigate to Virtual Networks > Subnets, and review NSG assignments. **Audit from Azure CLI** ``` az network nsg list --query "[].{Name:name, Rules:securityRules}" ``` **Audit from PowerShell** ``` Get-AzNetworkSecurityGroup -ResourceGroupName <resource-group-name> ``` | K10: TITLE:Implement and Manage a Firewall on Servers CONTROL:v8 4.4 DESCRIPTION:Implement and manage a firewall on servers, where supported. Example implementations include a virtual firewall, operating system firewall, or a third-party firewall agent.;TITLE:Apply Host-based Firewalls or Port Filtering CONTROL:v7 9.4 DESCRIPTION:Apply host-based firewalls or port filtering tools on end systems, with a default-deny rule that drops all traffic except those services and ports that are explicitly allowed.; | L10: 4.4 | O10: X | P10: X | Q10: X | R10: 9.4 | U10: X | V10: X | W10: X | X10: https://learn.microsoft.com/en-us/security/benchmark/azure/baselines/azure-databricks-security-baseline:https://learn.microsoft.com/en-us/azure/databricks/security/network/classic/vnet-inject#network-security-group-rules | Y10: By default, Databricks subnets do not have NSGs assigned.
A11: 2.1 | B11: 2.1.4 | C11: Ensure that users and groups are synced from Microsoft Entra ID to Azure Databricks | D11: Manual | E11: To ensure centralized identity and access management, users and groups from Microsoft Entra ID should be synchronized with Azure Databricks. This is achieved through SCIM provisioning, which automates the creation, update, and deactivation of users and groups in Databricks based on Entra ID assignments. Enabling this integration ensures that access controls in Databricks remain consistent with corporate identity governance policies, reducing the risk of orphaned accounts, stale permissions, and unauthorized access. | F11: Syncing users and groups from Microsoft Entra ID centralizes access control, enforces the least privilege principle by automatically revoking unnecessary access, reduces administrative overhead by eliminating manual user management, and ensures auditability and compliance with industry regulations. | G11: SCIM provisioning requires role mapping to avoid misconfigured user privileges. | H11: **Remediate from Azure Portal** Enable provisioning in Azure Portal: 1. Go to `Microsoft Entra ID`. 1. Under `Manage`, click `Enterprise applications`. 1. Click the name of the Azure Databricks SCIM application. 1. Under `Provisioning`, select `Automatic` and enter the SCIM endpoint and API token from Databricks. Enable provisioning in Databricks: 5. Navigate to `Admin Console` > `Identity and Access Management`. 6. Enable SCIM provisioning and generate an API token. Configure role assignments: 7. Ensure groups from Entra ID are mapped to appropriate Databricks roles. 8. Restrict administrative privileges to designated security groups. Regularly monitor sync logs: 9. Periodically review sync logs in Microsoft Entra ID and Databricks Admin Console. 10. Configure Azure Monitor alerts for provisioning failures. Disable manual user creation in Databricks: 11. Ensure that all user management is controlled via SCIM sync from Entra ID. 12. Disable personal access token usage for authentication. **Remediate from Azure CLI** Enable SCIM User and Group Provisioning in Azure Databricks: ``` az ad app update --id <databricks-app-id> --set provisioning.provisioningMode=Automatic ``` | I11: **Audit from Azure Portal** Verify SCIM provisioning is enabled: 1. Go to `Microsoft Entra ID`. 1. Under `Manage`, click `Enterprise applications`. 1. Click the name of the Azure Databricks SCIM application. 1. Under `Provisioning`, confirm that SCIM provisioning is enabled and running. Check user sync status in Azure Portal: 5. Under `Provisioning Logs`, verify the last successful sync and any failed entries. Check user sync status in Databricks: 6. Go to `Admin Console` > `Identity and Access Management`. 7. Confirm that Users and Groups match those assigned in Microsoft Entra ID. Ensure role-based access control (RBAC) mapping is correct: 8. Verify that users are assigned appropriate Databricks roles (e.g. Admin, User, Contributor). 9. Confirm that groups are mapped to workspace access roles. | K11: TITLE:Centralize Account Management CONTROL:v8 5.6 DESCRIPTION:Centralize account management through a directory or identity service.;TITLE:Configure Centralized Point of Authentication CONTROL:v7 16.2 DESCRIPTION:Configure access for all accounts through as few centralized points of authentication as possible, including network, security, and cloud systems.; | L11: 5.6 | P11: X | Q11: X | R11: 16.2 | V11: X | W11: X | X11: https://learn.microsoft.com/en-us/azure/databricks/administration-guide/users-groups/scim/aad | Y11: By default, Azure Databricks does not sync users and groups from Microsoft Entra ID.
A12: 2.1 | B12: 2.1.5 | C12: Ensure that Unity Catalog is configured for Azure Databricks | D12: Manual | E12: Unity Catalog is a centralized governance model for managing and securing data in Azure Databricks. It provides fine-grained access control to databases, tables, and views using Microsoft Entra ID identities. Unity Catalog also enhances data lineage, audit logging, and compliance monitoring, making it a critical component for security and governance. | F12: * Enforces centralized access control policies and reduces data security risks. * Enables identity-based authentication via Microsoft Entra ID. * Improves compliance with industry regulations (e.g. GDPR, HIPAA, SOC 2) by providing audit logs and access visibility. * Prevents unauthorized data access through table-, row-, and column-level security (RLS & CLS). | G12: * Improperly configured permissions may lead to data exfiltration or unauthorized access. * Unity Catalog requires structured governance policies to be effective and prevent overly permissive access. | H12: Use the remediation procedure written in this article: https://learn.microsoft.com/en-us/azure/databricks/data-governance/unity-catalog/get-started. | I12: Method 1: Verify unity catalog deployment: 1. As an Azure Databricks account admin, log into the account console. 1. Click Workspaces. 1. Find your workspace and check the Metastore column. If a metastore name is present, your workspace is attached to a Unity Catalog metastore and therefore enabled for Unity Catalog. Method 2: Run a SQL query to confirm Unity Catalog enablement Run the following SQL query in the SQL query editor or a notebook that is attached to a Unity Catalog-enabled compute resource. No admin role is required. ``` SELECT CURRENT_METASTORE(); ``` If the query returns a metastore ID like the following, then your workspace is attached to a Unity Catalog metastore and therefore enabled for Unity Catalog. | K12: TITLE:Centralize Account Management CONTROL:v8 5.6 DESCRIPTION:Centralize account management through a directory or identity service.;TITLE:Centralize Access Control CONTROL:v8 6.7 DESCRIPTION:Centralize access control for all enterprise assets through a directory service or SSO provider, where supported.;TITLE:Configure Centralized Point of Authentication CONTROL:v7 16.2 DESCRIPTION:Configure access for all accounts through as few centralized points of authentication as possible, including network, security, and cloud systems.; | L12: 5.6 | M12: 6.7 | P12: X | Q12: X | R12: 16.2 | V12: X | W12: X | X12: https://learn.microsoft.com/en-us/azure/databricks/data-governance/unity-catalog/:https://learn.microsoft.com/en-us/azure/databricks/admin/users-groups/:https://learn.microsoft.com/en-us/azure/databricks/data-governance/unity-catalog/enable-workspaces | Y12: New workspaces have Unity Catalog enabled by default. Existing workspaces may require manual enablement.
A13: 2.1 | B13: 2.1.6 | C13: Ensure that usage is restricted and expiry is enforced for Databricks personal access tokens | D13: Manual | E13: Databricks personal access tokens (PATs) provide API-based authentication for users and applications. By default, users can generate API tokens without expiration, leading to potential security risks if tokens are leaked, improperly stored, or not rotated regularly. To mitigate these risks, administrators should: * Restrict token creation to approved users and service principals. * Enforce expiration policies to prevent long-lived tokens. * Monitor token usage and revoke unused or compromised tokens. | F13: Restricting usage and enforcing expiry for personal access tokens reduces exposure to long-lived tokens, minimizes the risk of API abuse if compromised, and aligns with security best practices through controlled issuance and enforced expiry. | G13: If revoked improperly, applications relying on these tokens may fail, requiring a remediation plan for token rotation. Increased administrative effort is required to track and manage API tokens effectively. | H13: **Remediate from Azure Portal** Disable personal access tokens: If your workspace does not require PATs, you can disable them entirely to prevent their use.​ 1. Navigate to your Azure Databricks workspace. 1. Click the `Settings` icon and select `Admin Console`. 1. Go to the `Advanced` tab. 1. Under `Personal Access Tokens`, toggle the setting to `Disabled`. Databricks CLI: ``` databricks workspace-conf set-status --json '{"enableTokens": "false"}' ``` Control who can create and use personal access tokens: Define which users or groups are authorized to create and utilize PATs.​ 1. Navigate to your Azure Databricks workspace. 1. Click the `Settings` icon and select `Admin Console`. 1. Go to the `Advanced` tab. 1. Click on `Personal Access Tokens` and then `Permissions`. 1. Assign the appropriate permissions (e.g. No Permissions, Can Use, Can Manage) to users or groups. Set maximum lifetime for new personal access tokens: Limit the validity period of new tokens to reduce potential misuse.​ Databricks CLI: ``` databricks workspace-conf set-status --json '{"maxTokenLifetimeDays": "90"}' ``` Monitor and revoke personal access tokens: Periodically review active tokens and revoke any that are unnecessary or potentially compromised.​ Databricks CLI: ``` databricks token list ``` ``` databricks token delete --token-id <token-id> ``` Transition to OAuth for enhanced security: Utilize OAuth tokens for authentication, offering improved security features over PATs. | I13: Azure Databricks administrators can monitor and revoke personal access tokens within their workspace. Detailed instructions are available in the "Monitor and Revoke Personal Access Tokens" section of the Microsoft documentation: https://learn.microsoft.com/en-us/azure/databricks/admin/access-control/tokens. To evaluate the usage of personal access tokens in your Azure Databricks account, you can utilize the provided notebook that lists all PATs not rotated or updated in the last 90 days, allowing you to identify tokens that may require revocation. This process is detailed here: https://learn.microsoft.com/en-us/azure/databricks/admin/access-control/tokens. Implementing diagnostic logging provides a comprehensive reference of audit log services and events, enabling you to track activities related to personal access tokens. More information can be found in the diagnostic log reference section: https://learn.microsoft.com/en-us/azure/databricks/admin/account-settings/audit-logs. | K13: TITLE:Establish an Access Revoking Process CONTROL:v8 6.2 DESCRIPTION:Establish and follow a process, preferably automated, for revoking access to enterprise assets, through disabling accounts immediately upon termination, rights revocation, or role change of a user. Disabling accounts, instead of deleting accounts, may be necessary to preserve audit trails.;TITLE:Establish Process for Revoking Access CONTROL:v7 16.7 DESCRIPTION:Establish and follow an automated process for revoking system access by disabling accounts immediately upon termination or change of responsibilities of an employee or contractor . Disabling these accounts, instead of deleting accounts, allows preservation of audit trails.; | L13: 6.2 | O13: X | P13: X | Q13: X | R13: 16.7 | V13: X | W13: X | X13: https://learn.microsoft.com/en-us/azure/databricks/administration-guide/access-control/tokens:https://learn.microsoft.com/en-us/azure/databricks/dev-tools/auth/ | Y13: By default, personal access tokens are enabled and users can create the Personal access token and their expiry time.
A14: 2.1 | B14: 2.1.7 | C14: Ensure that diagnostic log delivery is configured for Azure Databricks | D14: Automated | E14: Azure Databricks Diagnostic Logging provides insights into system operations, user activities, and security events within a Databricks workspace. Enabling diagnostic logs helps organizations: * Detect security threats by logging access, job executions, and cluster activities. * Ensure compliance with industry regulations such as SOC 2, HIPAA, and GDPR. * Monitor operational performance and troubleshoot issues proactively. | F14: Diagnostic logging provides visibility into security and operational activities within Databricks workspaces while maintaining an audit trail for forensic investigations, and it supports compliance with regulatory standards that require logging and monitoring. | G14: Logs consume storage and may require additional monitoring tools, leading to increased operational overhead and costs. Incomplete log configurations may result in missing critical events, reducing monitoring effectiveness. | H14: **Remediate from Azure Portal** Enable diagnostic logging for Azure Databricks: 1. Navigate to your Azure Databricks workspace. 1. In the left-hand menu, select `Monitoring` > `Diagnostic settings`. 1. Click `+ Add diagnostic setting`. 1. Under `Category details`, select the log categories you wish to capture, such as AuditLogs, Clusters, Notebooks, and Jobs. 1. Choose a destination for the logs: - `Log Analytics workspace`: For advanced querying and monitoring. - `Storage account`: For long-term retention. - `Event Hub`: For integration with third-party systems. 1. Provide a `Name` for the diagnostic setting. 1. Click `Save`. Implement log retention policies: 1. Navigate to your Log Analytics workspace. 1. Under `General`, select `Usage and estimated costs`. 1. Click `Data Retention`. 1. Adjust the retention period slider to the desired number of days (up to 730 days). 1. Click `OK`. Monitor logs for anomalies: 1. Navigate to `Azure Monitor`. 1. Select `Alerts` > `+ New alert rule`. 1. Under `Scope`, specify the Databricks resource. 1. Define `Condition` based on log queries that identify anomalies (e.g. unauthorized access attempts). 1. Configure `Actions` to notify stakeholders or trigger automated responses. 1. Provide an Alert rule `name` and `description`. 1. Click `Create alert rule`. **Remediate from Azure CLI** Enable diagnostic logging for Azure Databricks: ``` az monitor diagnostic-settings create --name "DatabricksLogging" --resource <databricks-resource-id> --logs '[{"category": "accounts", "enabled": true}, {"category": "Clusters", "enabled": true}, {"category": "Notebooks", "enabled": true}, {"category": "Jobs", "enabled": true}]' --workspace <log-analytics-id> ``` Implement log retention policies: ``` az monitor log-analytics workspace update --resource-group <resource-group> --name <log-analytics-name> --retention-time 365 ``` Monitor logs for anomalies: ``` az monitor activity-log alert create --name "DatabricksAnomalyAlert" --resource-group <resource-group> --scopes <databricks-resource-id> --condition "contains 'UnauthorizedAccess'" ``` | I14: **Audit from Azure Portal** Check if diagnostic logging is enabled for the Databricks workspace: 1. Go to `Azure Databricks`. 1. Select a workspace. 1. In the left-hand menu, select `Monitoring` > `Diagnostic settings`. 1. Verify if a diagnostic setting is configured. If not, diagnostic logging is not enabled. Ensure that logging is enabled for the following categories:​ * `accounts`: User account activities. * `Filesystem`: Databricks Filesystem Logs * `clusters`: Cluster state changes and errors. * `notebook`: Execution events. * `jobs`: Job execution tracking. Verify that logs are being sent to one or more of the following destinations:​ * `Azure Log Analytics workspace`: For analysis and querying. * `Azure Storage Account`: For long-term retention. * `Azure Event Hubs`: For integration with SIEM tools. **Audit from Azure CLI** Check if diagnostic logging is enabled for the Databricks workspace: ``` az monitor diagnostic-settings list --resource <databricks-resource-id> ``` If the output is empty, no diagnostic settings are configured. Verify log categories being collected: ``` az monitor diagnostic-settings show --name <setting-name> --resource <databricks-resource-id> ``` Review the output to confirm that the necessary log categories are enabled. Check if logs are stored securely in an approved location: ``` az monitor diagnostic-settings list --resource <databricks-resource-id> ``` Review the storageAccountId, workspaceId, and eventHubAuthorizationRuleId fields in the output to confirm the log destinations. **Audit from PowerShell** Check if diagnostic logging is enabled for the Databricks workspace: ``` Get-AzDiagnosticSetting -ResourceId <databricks-resource-id> ``` An empty result indicates that diagnostic logging is not enabled. **Audit from Azure Policy** If referencing a digital copy of this Benchmark, clicking a Policy ID will open a link to the associated Policy definition in Azure. If referencing a printed copy, you can search Policy IDs from this URL: https://portal.azure.com/#view/Microsoft_Azure_Policy/PolicyMenuBlade/~/Definitions - **Policy ID:** [138ff14d-b687-4faa-a81c-898c91a87fa2](https://portal.azure.com/#view/Microsoft_Azure_Policy/PolicyDetailBlade/definitionId/%2Fproviders%2FMicrosoft.Authorization%2FpolicyDefinitions%2F138ff14d-b687-4faa-a81c-898c91a87fa2) **- Name:** 'Resource logs in Azure Databricks Workspaces should be enabled' | J14: * Ensure that the Azure Databricks workspace is on the Premium plan to utilize diagnostic logging features. * Regularly review and update alert rules to adapt to evolving security threats and operational requirements. | K14: TITLE:Collect Audit Logs CONTROL:v8 8.2 DESCRIPTION:Collect audit logs. Ensure that logging, per the enterprise’s audit log management process, has been enabled across enterprise assets.;TITLE:Activate audit logging CONTROL:v7 6.2 DESCRIPTION:Ensure that local logging has been enabled on all systems and networking devices.; | L14: 8.2 | O14: X | P14: X | Q14: X | R14: 6.2 | U14: X | V14: X | W14: X | X14: https://learn.microsoft.com/en-us/azure/databricks/admin/account-settings/audit-log-delivery:https://learn.microsoft.com/en-us/troubleshoot/azure/azure-monitor/log-analytics/billing/configure-data-retention:https://docs.azure.cn/en-us/databricks/admin/account-settings/audit-logs:https://learn.microsoft.com/en-us/azure/azure-monitor/reference/supported-logs/microsoft-databricks-workspaces-logs
A15: 2.1 | B15: 2.1.9 | C15: Ensure 'No Public IP' is set to 'Enabled' | D15: Automated | E15: Enable secure cluster connectivity (also known as no public IP) on Azure Databricks workspaces to ensure that clusters do not have public IP addresses and communicate with the control plane over a secure connection. | F15: Enabling secure cluster connectivity limits exposure to the public internet, improving security and reducing the risk of external attacks. | G15: Enabling secure cluster connectivity requires careful network configuration. Before secure cluster connectivity can be enabled, Azure Databricks workspaces must be deployed in a customer-managed virtual network (VNet injection)—refer to the recommendation `Ensure that Azure Databricks is deployed in a customer-managed virtual network (VNet)`. | H15: **Remediate from Azure Portal** 1. Go to `Azure Databricks`. 1. Click the name of a workspace. 1. Under `Settings`, click `Networking`. 1. Under `Network access`, next to `Deploy Azure Databricks workspace with Secure Cluster Connectivity (No Public IP)`, click the radio button next to `Enabled`. 1. Click `Save`. 1. Repeat steps 1-5 for each workspace requiring remediation. **Remediate from Azure CLI** For each workspace requiring remediation, run the following command to set `enableNoPublicIp` to `true`: ``` az databricks workspace update --resource-group <resource-group> --name <workspace> --enable-no-public-ip true ``` **Remediate from PowerShell** For each workspace requiring remediation, run the following command to set `EnableNoPublicIP` to `True`: ``` Update-AzDatabricksWorkspace -ResourceGroupName <resource-group> -Name <workspace> -EnableNoPublicIP ``` | I15: **Audit from Azure Portal** 1. Go to `Azure Databricks`. 1. Click the name of a workspace. 1. Under `Settings`, click `Networking`. 1. Under `Network access`, ensure that `Deploy Azure Databricks workspace with Secure Cluster Connectivity (No Public IP)` is set to `Enabled`. 1. Repeat steps 1-4 for each workspace. **Audit from Azure CLI** Run the following command to list workspaces: ``` az databricks workspace list ``` For each workspace, run the following command to get the `enableNoPublicIp` setting: ``` az databricks workspace show --resource-group <resource-group> --name <workspace> --query parameters.enableNoPublicIp.value ``` Ensure that `true` is returned. **Audit from PowerShell** Run the following command to list workspaces: ``` Get-AzDatabricksWorkspace ``` Run the following command to get the workspace in a resource group with a given name: ``` $workspace = Get-AzDatabricksWorkspace -ResourceGroupName <resource-group> -Name <workspace> ``` Run the following command to get the `EnableNoPublicIp` setting: ``` $workspace.EnableNoPublicIP ``` Ensure that `True` is returned. Repeat for each workspace. **Audit from Azure Policy** If referencing a digital copy of this Benchmark, clicking a Policy ID will open a link to the associated Policy definition in Azure. If referencing a printed copy, you can search Policy IDs from this URL: https://portal.azure.com/#view/Microsoft_Azure_Policy/PolicyMenuBlade/~/Definitions - **Policy ID:** [51c1490f-3319-459c-bbbc-7f391bbed753](https://portal.azure.com/#view/Microsoft_Azure_Policy/PolicyDetailBlade/definitionId/%2Fproviders%2FMicrosoft.Authorization%2FpolicyDefinitions%2F51c1490f-3319-459c-bbbc-7f391bbed753) **- Name:** 'Azure Databricks Clusters should disable public IP' | K15: TITLE:Configure Data Access Control Lists CONTROL:v8 3.3 DESCRIPTION:Configure data access control lists based on a user’s need to know. Apply data access control lists, also known as access permissions, to local and remote file systems, databases, and applications.;TITLE:Protect Information through Access Control Lists CONTROL:v7 14.6 DESCRIPTION:Protect all information stored on systems with file system, network share, claims, application, or database specific access control lists. These controls will enforce the principle that only authorized individuals should have access to the information based on their need to access the information as a part of their responsibilities.; | L15: 3.3 | O15: X | P15: X | Q15: X | R15: 14.6 | U15: X | V15: X | W15: X | X15: https://learn.microsoft.com/en-us/azure/databricks/security/network/classic/secure-cluster-connectivity:https://learn.microsoft.com/en-us/cli/azure/databricks/workspace:https://learn.microsoft.com/en-us/powershell/module/az.databricks | Y15: `No Public IP` is set to `Enabled` by default.
A16: 2.1 | B16: 2.1.10 | C16: Ensure 'Allow Public Network Access' is set to 'Disabled' | D16: Automated | E16: Disable public network access to prevent exposure to the internet and reduce the risk of unauthorized access. Use private endpoints to securely manage access within trusted networks. | F16: Disabling public network access improves security by ensuring that Azure Databricks workspaces are not exposed on the public internet. | G16: **NOTE:** Prior to disabling public network access, it is strongly recommended that, for each workspace, either: - virtual network integration is completed as described in **"Ensure that Azure Databricks is deployed in a customer-managed virtual network (VNet)"** OR - private endpoints/links are set up as described in **"Ensure private endpoints are used to access Azure Databricks workspaces."** Disabling public network access restricts access to the service. This enhances security but will require the configuration of a virtual network and/or private endpoints for any services or users needing access within trusted networks. Before public network access can be disabled, Azure Databricks workspaces must be deployed in a customer-managed virtual network (VNet injection)—refer to the recommendation `Ensure that Azure Databricks is deployed in a customer-managed virtual network (VNet)`, and `requiredNsgRules` must be set to a value other than `AllRules`. | H16: **Remediate from Azure Portal** 1. Go to `Azure Databricks`. 1. Click the name of a workspace. 1. Under `Settings` click `Networking`. 1. Under `Network access`, next to `Allow Public Network Access`, click the radio button next to `Disabled`. 1. Click `Save`. 1. Repeat steps 1-5 for each workspace requiring remediation. **Remediate from Azure CLI** For each workspace requiring remediation, run the following command to set `publicNetworkAccess` to `Disabled`: ``` az databricks workspace update --resource-group <resource-group> --name <workspace> --public-network-access Disabled ``` **Remediate from PowerShell** For each workspace requiring remediation, run the following command to set `PublicNetworkAccess` to `Disabled`: ``` Update-AzDatabricksWorkspace -ResourceGroupName <resource-group> -Name <workspace> -PublicNetworkAccess Disabled ``` | I16: **Audit from Azure Portal** 1. Go to `Azure Databricks`. 1. Click the name of a workspace. 1. Under `Settings` click `Networking`. 1. Under `Network access`, ensure `Allow Public Network Access` is set to `Disabled`. 1. Repeat steps 1-4 for each workspace. **Audit from Azure CLI** Run the following command to list workspaces: ``` az databricks workspace list ``` For each workspace, run the following command to get the `publicNetworkAccess` setting: ``` az databricks workspace show --resource-group <resource-group> --name <workspace> --query publicNetworkAccess ``` Ensure that `"Disabled"` is returned. **Audit from PowerShell** Run the following command to list workspaces: ``` Get-AzDatabricksWorkspace ``` Run the following command to get the workspace in a resource group with a given name: ``` $workspace = Get-AzDatabricksWorkspace -ResourceGroupName <resource-group> -Name <workspace> ``` Run the following command to get the `PublicNetworkAccess` setting: ``` $workspace.PublicNetworkAccess ``` Ensure that `Disabled` is returned. Repeat for each workspace. **Audit from Azure Policy** If referencing a digital copy of this Benchmark, clicking a Policy ID will open a link to the associated Policy definition in Azure. If referencing a printed copy, you can search Policy IDs from this URL: https://portal.azure.com/#view/Microsoft_Azure_Policy/PolicyMenuBlade/~/Definitions - **Policy ID:** [0e7849de-b939-4c50-ab48-fc6b0f5eeba2](https://portal.azure.com/#view/Microsoft_Azure_Policy/PolicyDetailBlade/definitionId/%2Fproviders%2FMicrosoft.Authorization%2FpolicyDefinitions%2F0e7849de-b939-4c50-ab48-fc6b0f5eeba2) **- Name:** 'Azure Databricks Workspaces should disable public network access' | J16: This recommendation is based on the Common Reference Recommendation `Ensure public network access is Disabled`, from the `Common Reference Recommendations > Networking > Virtual Networks (VNets)` section. | K16: TITLE:Configure Data Access Control Lists CONTROL:v8 3.3 DESCRIPTION:Configure data access control lists based on a user’s need to know. Apply data access control lists, also known as access permissions, to local and remote file systems, databases, and applications.;TITLE:Protect Information through Access Control Lists CONTROL:v7 14.6 DESCRIPTION:Protect all information stored on systems with file system, network share, claims, application, or database specific access control lists. These controls will enforce the principle that only authorized individuals should have access to the information based on their need to access the information as a part of their responsibilities.; | L16: 3.3 | O16: X | P16: X | Q16: X | R16: 14.6 | U16: X | V16: X | W16: X | X16: https://learn.microsoft.com/en-us/cli/azure/databricks/workspace:https://learn.microsoft.com/en-us/powershell/module/az.databricks | Y16: `Allow Public Network Access` is set to `Enabled` by default.
A17: 3 | C17: Compute Services | E17: **SERVICE CATEGORY BENCHMARK AVAILABLE**: - "CIS Microsoft Azure Compute Services Benchmark" To better understand the relationship between the Foundations Benchmark and Services Benchmarks, please read the "Introduction" section of this document. `PARTIAL RELOCATION - BE ADVISED!` Some recommendations previously covered in the CIS Microsoft Azure Foundations Benchmark (this document) related to Compute services have been relocated to a Benchmark titled **CIS Microsoft Azure Compute Services Benchmark**. This Compute Services section now provides a **foundational set** of secure configuration recommendations for products from Azure Product Directory's "Compute" category of services. After applying foundational recommendations, take inventory of the entire set of Compute Services in use by your organization, then look to the Benchmarks section of the CIS Microsoft Azure Community (https://workbench.cisecurity.org/communities/72) for defense-in-depth guidance for those specific services in the **CIS Microsoft Azure Compute Services Benchmark**. Services addressed in the **CIS Microsoft Azure Compute Services Benchmark**: - App Service - Azure Container Instances - Azure CycleCloud - Azure Dedicated Host - Azure Functions - Azure Kubernetes Service (AKS) - Azure Quantum - Azure Service Fabric - Azure Spot Virtual Machines - Azure Spring Apps - Azure Virtual Desktop - Azure VM Image Builder - Azure VMware Solution - Batch - Cloud Services - Linux Virtual Machines - SQL Server on Azure Virtual Machines - Static Web Apps - Virtual Machine Scale Sets - Virtual Machines Azure Product Directory Reference: https://azure.microsoft.com/en-us/products#compute **FEEDBACK REQUEST:** Is there a specific service or recommendation in this section that you'd like to see addressed or improved? Let us know by making a ticket or starting a discussion in the CIS Microsoft Azure Community (https://workbench.cisecurity.org/communities/72).
A18: 3.1 | C18: Virtual Machines | E18: This section covers security recommendations to follow for the configuration of Virtual Machines on an Azure subscription.
A19: 4 | C19: Database Services (reference) | E19: **SERVICE CATEGORY BENCHMARK AVAILABLE**: - "CIS Microsoft Azure Database Services Benchmark" To better understand the relationship between the Foundations Benchmark and Services Benchmarks, please read the "Introduction" section of this document. `FULL RELOCATION - BE ADVISED!` **- ALL -** recommendations previously covered in the CIS Microsoft Azure Foundations Benchmark (this document) related to products in the Database category of services have been relocated to a Benchmark titled **CIS Microsoft Azure Database Services Benchmark**. This section now serves only as a reference. Services addressed in the **CIS Microsoft Azure Database Services Benchmark**: - Azure Cache for Redis - Azure Cosmos DB - Azure Data Factory - Azure Database for MariaDB - Azure Database for MySQL - Azure Database for PostgreSQL - Azure Database Migration Service - Azure SQL - Azure SQL Database - Azure SQL Edge - Azure SQL Managed Instance - SQL Server on Azure Virtual Machines - Table Storage - Azure Managed Instance for Apache Cassandra - Azure confidential ledger Azure Product Directory Reference: https://azure.microsoft.com/en-us/products#databases **FEEDBACK REQUEST:** Is there a specific service or recommendation in this section that you'd like to see addressed or improved? Let us know by making a ticket or starting a discussion in the CIS Microsoft Azure Community (https://workbench.cisecurity.org/communities/72).
A20: 5 | C20: Identity Services | E20: To better understand the relationship between the Foundations Benchmark and Services Benchmarks, please read the "Introduction" section of this document. This section covers security best practice recommendations for products in the Azure Identity services category. Azure Product Directory Reference: https://azure.microsoft.com/en-us/products#identity **FEEDBACK REQUEST:** Is there a specific service or recommendation in this section that you'd like to see addressed or improved? Let us know by making a ticket or starting a discussion in the CIS Microsoft Azure Community (https://workbench.cisecurity.org/communities/72).
A21: 5 | B21: 5.4 | C21: Ensure that 'Restrict non-admin users from creating tenants' is set to 'Yes' | D21: Automated | E21: Require administrators or appropriately delegated users to create new tenants. | F21: It is recommended to only allow an administrator to create new tenants. This prevent users from creating new Microsoft Entra ID or Azure AD B2C tenants and ensures that only authorized users are able to do so. | G21: Enforcing this setting will ensure that only authorized users are able to create new tenants. | H21: **Remediate from Azure Portal** 1. From Azure Home select the Portal Menu 1. Select `Microsoft Entra ID` 1. Under `Manage`, select `Users` 1. Under `Manage`, select `User settings` 1. Set `Restrict non-admin users from creating tenants ` to `Yes` 1. Click `Save` **Remediate from PowerShell** ``` Import-Module Microsoft.Graph.Identity.SignIns Connect-MgGraph -Scopes 'Policy.ReadWrite.Authorization' Select-MgProfile -Name beta $params = @{ DefaultUserRolePermissions = @{ AllowedToCreateTenants = $false } } Update-MgPolicyAuthorizationPolicy -AuthorizationPolicyId -BodyParameter $params ``` | I21: **Audit from Azure Portal** 1. From Azure Home select the Portal Menu 1. Select `Microsoft Entra ID` 1. Under `Manage`, select `Users` 1. Under `Manage`, select `User settings` 1. Ensure that `Restrict non-admin users from creating tenants` is set to `Yes` **Audit from PowerShell** ``` Import-Module Microsoft.Graph.Identity.SignIns Connect-MgGraph -Scopes 'Policy.ReadWrite.Authorization' Get-MgPolicyAuthorizationPolicy | Select-Object -ExpandProperty DefaultUserRolePermissions | Format-List ``` Review the "DefaultUserRolePermissions" section of the output. Ensure that `AllowedToCreateTenants` is not `"True"`. | K21: TITLE:Define and Maintain Role-Based Access Control CONTROL:v8 6.8 DESCRIPTION:Define and maintain role-based access control, through determining and documenting the access rights necessary for each role within the enterprise to successfully carry out its assigned duties. Perform access control reviews of enterprise assets to validate that all privileges are authorized, on a recurring schedule at a minimum annually, or more frequently.;TITLE:Protect Information through Access Control Lists CONTROL:v7 14.6 DESCRIPTION:Protect all information stored on systems with file system, network share, claims, application, or database specific access control lists. These controls will enforce the principle that only authorized individuals should have access to the information based on their need to access the information as a part of their responsibilities.; | L21: 6.8 | Q21: X | R21: 14.6 | U21: X | V21: X | W21: X | X21: https://learn.microsoft.com/en-us/entra/fundamentals/users-default-permissions:https://learn.microsoft.com/en-us/entra/identity/role-based-access-control/permissions-reference#tenant-creator:https://blog.admindroid.com/disable-users-creating-new-azure-ad-tenants-in-microsoft-365/
A22: 5 | B22: 5.5 | C22: Ensure that 'Number of methods required to reset' is set to '2' | D22: Manual | E22: Ensures that two alternate forms of identification are provided before allowing a password reset. | F22: A Self-service Password Reset (SSPR) through Azure Multi-factor Authentication (MFA) ensures the user's identity is confirmed using two separate methods of identification. With multiple methods set, an attacker would have to compromise both methods before they could maliciously reset a user's password. | G22: There may be administrative overhead, as users who lose access to their secondary authentication methods will need an administrator with permissions to remove it. There will also need to be organization-wide security policies and training to teach administrators to verify the identity of the requesting user so that social engineering cannot render this setting useless. | H22: **Remediate from Azure Portal** 1. From Azure Home select the Portal Menu 1. Select `Microsoft Entra ID` 1. Under `Manage`, select `Users` 1. Under `Manage`, select `Password reset` 1. Select `Authentication methods` 1. Set the `Number of methods required to reset` to `2` 1. Click `Save` | I22: **Audit from Azure Portal** 1. From Azure Home select the Portal Menu 1. Select `Microsoft Entra ID` 1. Under `Manage`, select `Users` 1. Under `Manage`, select `Password reset` 1. Select `Authentication methods` 1. Ensure that `Number of methods required to reset` is set to `2` | K22: TITLE:Require MFA for Externally-Exposed Applications CONTROL:v8 6.3 DESCRIPTION:Require all externally-exposed enterprise or third-party applications to enforce MFA, where supported. Enforcing MFA through a directory service or SSO provider is a satisfactory implementation of this Safeguard.;TITLE:Require MFA for Remote Network Access CONTROL:v8 6.4 DESCRIPTION:Require MFA for remote network access.;TITLE:Require Multi-factor Authentication CONTROL:v7 16.3 DESCRIPTION:Require multi-factor authentication for all user accounts, on all systems, whether managed onsite or by a third-party provider.; | L22: 6.3 | M22: 6.4 | O22: X | P22: X | Q22: X | R22: 16.3 | V22: X | W22: X | X22: https://learn.microsoft.com/en-us/entra/identity/authentication/tutorial-enable-sspr:https://learn.microsoft.com/en-us/entra/identity/authentication/concept-registration-mfa-sspr-combined:https://learn.microsoft.com/en-us/security/benchmark/azure/mcsb-identity-management#im-6-use-strong-authentication-controls:https://learn.microsoft.com/en-us/entra/identity/authentication/passwords-faq#password-reset-registration:https://support.microsoft.com/en-us/account-billing/reset-your-work-or-school-password-using-security-info-23dde81f-08bb-4776-ba72-e6b72b9dda9e:https://learn.microsoft.com/en-us/entra/identity/authentication/concept-authentication-methods | Y22: By default, the `Number of methods required to reset` is `1`.
A23: 5 | B23: 5.6 | C23: Ensure that account 'Lockout threshold' is less than or equal to '10' | D23: Manual | E23: The account lockout threshold determines how many failed login attempts are permitted prior to placing the account in a locked-out state and initiating a variable lockout duration. | F23: Account lockout is a method of protecting against brute-force and password spray attacks. Once the lockout threshold has been exceeded, the account enters a locked-out state which prevents all login attempts for a variable duration. The lockout in combination with a reasonable duration reduces the total number of failed login attempts that a malicious actor can execute in a given period of time. | G23: If account lockout threshold is set too low (less than 3), users may experience frequent lockout events and the resulting security alerts may contribute to alert fatigue. If account lockout threshold is set too high (more than 10), malicious actors can programmatically execute more password attempts in a given period of time. | H23: **Remediate from Azure Portal** 1. From Azure Home select the Portal Menu. 1. Select `Microsoft Entra ID`. 1. Under `Manage`, select `Security`. 1. Under `Manage`, select `Authentication methods`. 1. Under `Manage`, select `Password protection`. 1. Set the `Lockout threshold` to `10` or fewer. 1. Click `Save`. **Remediate from PowerShell** ``` Connect-MgGraph -Scopes "Policy.ReadWrite.AuthenticationMethod" Update-MgPolicyAuthenticationMethodsPolicy -PasswordProtection @{ LockoutThreshold = 10 LockoutDuration = "PT1M" } ``` **Remediate from Azure CLI** ``` az rest --method patch \ --url 'https://graph.microsoft.com/v1.0/policies/authenticationMethodsPolicy' \ --headers 'Content-Type=application/json' \ --body '{"passwordProtection":{"lockoutThreshold":10,"lockoutDuration":"PT1M"}}' ``` | I23: **Audit from Azure Portal** 1. From Azure Home select the Portal Menu. 1. Select `Microsoft Entra ID`. 1. Under `Manage`, select `Security`. 1. Under `Manage`, select `Authentication methods`. 1. Under `Manage`, select `Password protection`. 1. Ensure that `Lockout threshold` is set to `10` or fewer. **Audit from PowerShell** ``` Connect-MgGraph -Scopes "Policy.ReadWrite.AuthenticationMethod" $p = (Get-MgPolicyAuthenticationMethodsPolicy).PasswordProtection if ($p.LockoutThreshold -gt 10) { Update-MgPolicyAuthenticationMethodsPolicy -BodyParameter @{ passwordProtection = @{ lockoutThreshold = 10 lockoutDuration = [Math]::Max($p.LockoutDuration, 60) } } } Disconnect-MgGraph ``` **Audit from Azure CLI** ``` az rest --method get \ --url 'https://graph.microsoft.com/v1.0/policies/authenticationMethodsPolicy' \ --query 'passwordProtection.lockoutThreshold' ``` | J23: **NOTE:** The variable number for failed login attempts allowed before lockout is prescribed by many security and compliance frameworks. The **appropriate** setting for this variable should be determined by the most restrictive security or compliance framework that your organization follows. | K23: TITLE:Enforce Automatic Device Lockout on Portable End-User Devices CONTROL:v8 4.10 DESCRIPTION:Enforce automatic device lockout following a predetermined threshold of local failed authentication attempts on portable end-user devices, where supported. For laptops, do not allow more than 20 failed authentication attempts; for tablets and smartphones, no more than 10 failed authentication attempts. Example implementations include Microsoft® InTune Device Lock and Apple® Configuration Profile maxFailedAttempts.; | L23: 4.10 | P23: X | Q23: X | X23: https://learn.microsoft.com/en-us/entra/identity/authentication/howto-password-smart-lockout#manage-microsoft-entra-smart-lockout-values | Y23: By default, Lockout threshold is set to `10`.
A24: 5 | B24: 5.7 | C24: Ensure that account 'Lockout duration in seconds' is greater than or equal to '60' | D24: Manual | E24: The account lockout duration value determines how long an account retains the status of lockout, and therefore how long before a user can continue to attempt to login after passing the lockout threshold. | F24: Account lockout is a method of protecting against brute-force and password spray attacks. Once the lockout threshold has been exceeded, the account enters a locked-out state which prevents all login attempts for a variable duration. The lockout in combination with a reasonable duration reduces the total number of failed login attempts that a malicious actor can execute in a given period of time. | G24: If account lockout duration is set too low (less than 60 seconds), malicious actors can perform more password spray and brute-force attempts over a given period of time. If the account lockout duration is set too high (more than 300 seconds) users may experience inconvenient delays during lockout. | H24: **Remediate from Azure Portal** 1. From Azure Home select the Portal Menu. 1. Select `Microsoft Entra ID`. 1. Under `Manage`, select `Security`. 1. Under `Manage`, select `Authentication methods`. 1. Under `Manage`, select `Password protection`. 1. Set the `Lockout duration in seconds` to `60` or higher. 1. Click `Save`. | I24: **Audit from Azure Portal** 1. From Azure Home select the Portal Menu. 1. Select `Microsoft Entra ID`. 1. Under `Manage`, select `Security`. 1. Under `Manage`, select `Authentication methods`. 1. Under `Manage`, select `Password protection`. 1. Ensure that `Lockout duration in seconds` is set to `60` or higher. | K24: TITLE:Enforce Automatic Device Lockout on Portable End-User Devices CONTROL:v8 4.10 DESCRIPTION:Enforce automatic device lockout following a predetermined threshold of local failed authentication attempts on portable end-user devices, where supported. For laptops, do not allow more than 20 failed authentication attempts; for tablets and smartphones, no more than 10 failed authentication attempts. Example implementations include Microsoft® InTune Device Lock and Apple® Configuration Profile maxFailedAttempts.; | L24: 4.10 | P24: X | Q24: X | X24: https://learn.microsoft.com/en-us/entra/identity/authentication/howto-password-smart-lockout#manage-microsoft-entra-smart-lockout-values | Y24: By default, Lockout duration in seconds is set to `60`.
A25: 5 | B25: 5.8 | C25: Ensure that a 'Custom banned password list' is set to 'Enforce' | D25: Manual | E25: Microsoft Azure applies a default global banned password list to all user and admin accounts that are created and managed directly in Microsoft Entra ID. The Microsoft Entra password policy does not apply to user accounts that are synchronized from an on-premises Active Directory environment, unless Microsoft Entra ID Connect is used and `EnforceCloudPasswordPolicyForPasswordSyncedUsers` is enabled. Review the `Default Value` section for more detail on the password policy. For increased password security, a custom banned password list is recommended | F25: Implementing a custom banned password list gives your organization further control over the password policy. Disallowing easy-to-guess passwords increases the security of your Azure resources. | G25: Increasing password complexity may increase user account administration overhead. Utilizing the default global banned password list and a custom list requires a Microsoft Entra ID P1 or P2 license. On-premises Active Directory Domain Services users who aren't synchronized to Microsoft Entra ID still benefit from Microsoft Entra ID Password Protection based on the existing licensing of synchronized users. | H25: **Remediate from Azure Portal** 1. From Azure Home select the Portal Menu. 1. Select `Microsoft Entra ID`. 1. Under `Manage`, select `Security`. 1. Under `Manage`, select `Authentication methods`. 1. Under `Manage`, select `Password protection`. 1. Set the `Enforce custom list` option to `Yes`. 1. Click in the `Custom banned password list` text box. 1. Add a list of words, one per line, to prevent users from using in passwords. 1. Click `Save`. | I25: **Audit from Azure Portal** 1. From Azure Home select the Portal Menu. 1. Select `Microsoft Entra ID`. 1. Under `Manage`, select `Security`. 1. Under `Manage`, select `Authentication methods`. 1. Under `Manage`, select `Password protection`. 1. Ensure `Enforce custom list` is set to `Yes`. 1. Review the list of words banned from use in passwords. | K25: TITLE:Use Unique Passwords CONTROL:v8 5.2 DESCRIPTION:Use unique passwords for all enterprise assets. Best practice implementation includes, at a minimum, an 8-character password for accounts using MFA and a 14-character password for accounts not using MFA. ;TITLE:Centralize Access Control CONTROL:v8 6.7 DESCRIPTION:Centralize access control for all enterprise assets through a directory service or SSO provider, where supported.;TITLE:Use Unique Passwords CONTROL:v7 4.4 DESCRIPTION:Where multi-factor authentication is not supported (such as local administrator, root, or service accounts), accounts will use passwords that are unique to that system.; | L25: 5.2 | M25: 6.7 | O25: X | P25: X | Q25: X | R25: 4.4 | V25: X | W25: X | X25: https://learn.microsoft.com/en-us/entra/identity/authentication/concept-password-ban-bad-combined-policy:https://learn.microsoft.com/en-us/entra/identity/authentication/concept-password-ban-bad:https://learn.microsoft.com/en-us/powershell/module/azuread/:https://www.microsoft.com/en-us/research/publication/password-guidance/:https://learn.microsoft.com/en-us/entra/identity/authentication/tutorial-configure-custom-password-protection:https://learn.microsoft.com/en-us/security/benchmark/azure/mcsb-identity-management#im-6-use-strong-authentication-controls | Y25: By default the custom banned password list is not 'Enabled'. Organization-specific terms can be added to the custom banned password list, such as the following examples: - Brand names - Product names - Locations, such as company headquarters - Company-specific terms - Abbreviations that have specific company meaning - Months and weekdays with your company's local languages The default global banned password list is already applied to your resources which applies the following basic requirements: **Characters allowed:** - Uppercase characters (A - Z) - Lowercase characters (a - z) - Numbers (0 - 9) - Symbols: - @ # $ % ^ & * - _ ! + = [ ] { } | \ : ' , . ? / ` ~ " ( ) ; < > - blank space **Characters not allowed:** - Unicode characters **Password length:** Passwords require: - A minimum of eight characters - A maximum of 256 characters **Password complexity:** Passwords require three out of four of the following categories: - Uppercase characters - Lowercase characters - Numbers - Symbols Note: Password complexity check isn't required for Education tenants. **Password not recently used:** - When a user changes or resets their password, the new password can't be the same as the current or recently used passwords. - Password isn't banned by Entra ID Password Protection. - The password can't be on the global list of banned passwords for Azure AD Password Protection, or on the customizable list of banned passwords specific to your organization. **Evaluation** New passwords are evaluated for strength and complexity by validating against the combined list of terms from the global and custom banned password lists. Even if a user's password contains a banned password, the password may be accepted if the overall password is otherwise strong enough.
A26: 5 | B26: 5.9 | C26: Ensure that 'Number of days before users are asked to re-confirm their authentication information' is not set to '0' | D26: Manual | E26: Ensure that the number of days before users are asked to re-confirm their authentication information is not set to 0. | F26: This setting is necessary if 'Require users to register when signing in' is enabled. If authentication re-confirmation is disabled, registered users will never be prompted to re-confirm their existing authentication information. If the authentication information for a user changes, such as a phone number or email, then the password reset information for that user reverts to the previously registered authentication information. | G26: Users will be prompted to re-confirm their authentication information after the number of days specified. | H26: **Remediate from Azure Portal** 1. From Azure Home select the Portal Menu. 1. Select `Microsoft Entra ID`. 1. Under `Manage`, select `Users`. 1. Select `Password reset`. 1. Under `Manage`, select `Registration`. 1. Set the `Number of days before users are asked to re-confirm their authentication information` to your organization-defined frequency. 1. Click `Save`. | I26: **Audit from Azure Portal** 1. From Azure Home select the Portal Menu. 1. Select `Microsoft Entra ID`. 1. Under `Manage`, select `Users`. 1. Select `Password reset`. 1. Under `Manage`, select `Registration`. 1. Ensure that `Number of days before users are asked to re-confirm their authentication information` is not set to `0`. | K26: TITLE:Establish an Access Revoking Process CONTROL:v8 6.2 DESCRIPTION:Establish and follow a process, preferably automated, for revoking access to enterprise assets, through disabling accounts immediately upon termination, rights revocation, or role change of a user. Disabling accounts, instead of deleting accounts, may be necessary to preserve audit trails.;TITLE:Ensure All Accounts Have An Expiration Date CONTROL:v7 16.10 DESCRIPTION:Ensure that all accounts have an expiration date that is monitored and enforced.; | L26: 6.2 | O26: X | P26: X | Q26: X | R26: 16.10 | V26: X | W26: X | X26: https://learn.microsoft.com/en-us/entra/identity/authentication/concept-sspr-howitworks#registration:https://support.microsoft.com/en-us/account-billing/reset-your-work-or-school-password-using-security-info-23dde81f-08bb-4776-ba72-e6b72b9dda9e:https://learn.microsoft.com/en-us/security/benchmark/azure/mcsb-governance-strategy#gs-6-define-and-implement-identity-and-privileged-access-strategy:https://learn.microsoft.com/en-us/entra/identity/authentication/concept-authentication-methods | Y26: By default, the `Number of days before users are asked to re-confirm their authentication information` is set to "180 days".
A27: 5 | B27: 5.10 | C27: Ensure that 'Notify users on password resets?' is set to 'Yes' | D27: Manual | E27: Ensure that users are notified on their primary and alternate emails on password resets. | F27: User notification on password reset is a proactive way of confirming password reset activity. It helps the user to recognize unauthorized password reset activities. | G27: Users will receive emails alerting them to password changes to both their primary and alternate emails. | H27: **Remediate from Azure Portal** 1. From Azure Home select the Portal Menu 1. Select `Microsoft Entra ID` 1. Under `Manage`, select `Users` 1. Under `Manage`, select `Password reset` 1. Under `Manage`, select `Notifications` 1. Set `Notify users on password resets?` to `Yes` 1. Click `Save` | I27: **Audit from Azure Portal** 1. From Azure Home select the Portal Menu 1. Select `Microsoft Entra ID` 1. Under `Manage`, select `Users` 1. Under `Manage`, select `Password reset` 1. Under `Manage`, select `Notifications` 1. Ensure that `Notify users on password resets?` is set to `Yes` | K27: TITLE:Centralize Access Control CONTROL:v8 6.7 DESCRIPTION:Centralize access control for all enterprise assets through a directory service or SSO provider, where supported.;TITLE:Configure Centralized Point of Authentication CONTROL:v7 16.2 DESCRIPTION:Configure access for all accounts through as few centralized points of authentication as possible, including network, security, and cloud systems.; | L27: 6.7 | P27: X | Q27: X | R27: 16.2 | V27: X | W27: X | X27: https://learn.microsoft.com/en-us/entra/identity/authentication/tutorial-enable-sspr#set-up-notifications-and-customizations:https://learn.microsoft.com/en-us/entra/identity/authentication/concept-sspr-howitworks#notifications:https://support.microsoft.com/en-us/account-billing/reset-your-work-or-school-password-using-security-info-23dde81f-08bb-4776-ba72-e6b72b9dda9e:https://learn.microsoft.com/en-us/security/benchmark/azure/mcsb-governance-strategy#gs-6-define-and-implement-identity-and-privileged-access-strategy | Y27: By default, `Notify users on password resets?` is set to "Yes".
A28: 5 | B28: 5.11 | C28: Ensure that 'Notify all admins when other admins reset their password?' is set to 'Yes' | D28: Manual | E28: Ensure that all Global Administrators are notified if any other administrator resets their password. | F28: Administrator accounts are sensitive. Any password reset activity notification, when sent to all Administrators, ensures that all Global Administrators can passively confirm if such a reset is a common pattern within their group. For example, if all Administrators change their password every 30 days, any password reset activity before that may require administrator(s) to evaluate any unusual activity and confirm its origin. | G28: All Global Administrators will receive a notification from Azure every time a password is reset. This is useful for auditing procedures to confirm that there are no out of the ordinary password resets for Administrators. There is additional overhead, however, in the time required for Global Administrators to audit the notifications. This setting is only useful if all Global Administrators pay attention to the notifications and audit each one. | H28: **Remediate from Azure Portal** 1. From Azure Home select the Portal Menu 1. Select `Microsoft Entra ID` 1. Under `Manage`, select `Users` 1. Under `Manage`, select `Password reset` 1. Under `Manage`, select `Notifications` 1. Set `Notify all admins when other admins reset their password?` to `Yes` 1. Click `Save` | I28: **Audit from Azure Portal** 1. From Azure Home select the Portal Menu 1. Select `Microsoft Entra ID` 1. Under `Manage`, select `Users` 1. Under `Manage`, select `Password reset` 1. Under `Manage`, select `Notifications` 1. Ensure that `Notify all admins when other admins reset their password?` is set to `Yes` | K28: TITLE:Restrict Administrator Privileges to Dedicated Administrator Accounts CONTROL:v8 5.4 DESCRIPTION:Restrict administrator privileges to dedicated administrator accounts on enterprise assets. Conduct general computing activities, such as internet browsing, email, and productivity suite use, from the user’s primary, non-privileged account.;TITLE:Centralize Access Control CONTROL:v8 6.7 DESCRIPTION:Centralize access control for all enterprise assets through a directory service or SSO provider, where supported.;TITLE:Log and Alert on Changes to Administrative Group Membership CONTROL:v7 4.8 DESCRIPTION:Configure systems to issue a log entry and alert when an account is added to or removed from any group assigned administrative privileges.; | L28: 5.4 | M28: 6.7 | O28: X | P28: X | Q28: X | R28: 4.8 | V28: X | W28: X | X28: https://learn.microsoft.com/en-us/entra/identity/authentication/concept-sspr-howitworks#notifications:https://support.microsoft.com/en-us/account-billing/reset-your-work-or-school-password-using-security-info-23dde81f-08bb-4776-ba72-e6b72b9dda9e:https://learn.microsoft.com/en-us/security/benchmark/azure/mcsb-governance-strategy#gs-6-define-and-implement-identity-and-privileged-access-strategy:https://learn.microsoft.com/en-us/security/benchmark/azure/mcsb-privileged-access#pa-1-separate-and-limit-highly-privilegedadministrative-users:https://learn.microsoft.com/en-us/entra/identity/authentication/tutorial-enable-sspr#set-up-notifications-and-customizations | Y28: By default, `Notify all admins when other admins reset their password?` is set to "No".
A29: 5 | B29: 5.12 | C29: Ensure that 'User consent for applications' is set to 'Do not allow user consent' | D29: Manual | E29: Require administrators to provide consent for applications before use. | F29: If Microsoft Entra ID is running as an identity provider for third-party applications, permissions and consent should be limited to administrators or pre-approved. Malicious applications may attempt to exfiltrate data or abuse privileged user accounts. | G29: Enforcing this setting may create additional requests that administrators need to review. | H29: **Remediate from Azure Portal** 1. From Azure Home select the Portal Menu 1. Select `Microsoft Entra ID` 1. Under `Manage`, select `Enterprise applications` 1. Under `Security`, select `Consent and permissions` 1. Under `Manage`, select `User consent settings` 1. Set `User consent for applications` to `Do not allow user consent` 1. Click `Save` | I29: **Audit from Azure Portal** 1. From Azure Home select the Portal Menu 1. Select `Microsoft Entra ID` 1. Under `Manage`, select `Enterprise applications` 1. Under `Security`, select `Consent and permissions` 1. Under `Manage`, select `User consent settings` 1. Ensure `User consent for applications` is set to `Do not allow user consent` **Audit from PowerShell** ``` Connect-MgGraph (Get-MgPolicyAuthorizationPolicy).DefaultUserRolePermissions | Select-Object -ExpandProperty PermissionGrantPoliciesAssigned ``` If the command returns no values in response, the configuration complies with the recommendation. | K29: TITLE:Address Unauthorized Software CONTROL:v8 2.3 DESCRIPTION:Ensure that unauthorized software is either removed from use on enterprise assets or receives a documented exception. Review monthly, or more frequently.;TITLE:Establish an Access Granting Process CONTROL:v8 6.1 DESCRIPTION:Establish and follow a process, preferably automated, for granting access to enterprise assets upon new hire, rights grant, or role change of a user.;TITLE:Address unapproved software CONTROL:v7 2.6 DESCRIPTION:Ensure that unauthorized software is either removed or the inventory is updated in a timely manner; | L29: 2.3 | M29: 6.1 | O29: X | P29: X | Q29: X | R29: 2.6 | U29: X | V29: X | W29: X | X29: https://learn.microsoft.com/en-us/entra/identity/enterprise-apps/configure-user-consent?pivots=ms-powershell#configure-user-consent-to-applications:https://learn.microsoft.com/en-us/security/benchmark/azure/mcsb-privileged-access#pa-1-separate-and-limit-highly-privilegedadministrative-users:https://learn.microsoft.com/en-us/security/benchmark/azure/mcsb-governance-strategy#gs-2-define-and-implement-enterprise-segmentationseparation-of-duties-strategy:https://learn.microsoft.com/en-us/security/benchmark/azure/mcsb-governance-strategy#gs-6-define-and-implement-identity-and-privileged-access-strategy | Y29: By default, `Users consent for applications` is set to `Allow user consent for apps`.
A30: 5 | B30: 5.14 | C30: Ensure that 'Users can register applications' is set to 'No' | D30: Automated | E30: Require administrators or appropriately delegated users to register third-party applications. | F30: It is recommended to only allow an administrator to register custom-developed applications. This ensures that the application undergoes a formal security review and approval process prior to exposing Microsoft Entra ID data. Certain users like developers or other high-request users may also be delegated permissions to prevent them from waiting on an administrative user. Your organization should review your policies and decide your needs. | G30: Enforcing this setting will create additional requests for approval that will need to be addressed by an administrator. If permissions are delegated, a user may approve a malevolent third party application, potentially giving it access to your data. | H30: **Remediate from Azure Portal** 1. From Azure Home select the Portal Menu 1. Select `Microsoft Entra ID` 1. Under `Manage`, select `Users` 1. Under `Manage`, select `User settings` 1. Set `Users can register applications` to `No` 1. Click `Save` **Remediate from PowerShell** ``` $param = @{ AllowedToCreateApps = "$false" } Update-MgPolicyAuthorizationPolicy -DefaultUserRolePermissions $param ``` | I30: **Audit from Azure Portal** 1. From Azure Home select the Portal Menu 1. Select `Microsoft Entra ID` 1. Under `Manage`, select `Users` 1. Under `Manage`, select `User settings` 1. Ensure that `Users can register applications` is set to `No` **Audit from PowerShell** ``` (Get-MgPolicyAuthorizationPolicy).DefaultUserRolePermissions | Format-List AllowedToCreateApps ``` Command should return the value of `False` | K30: TITLE:Address Unauthorized Software CONTROL:v8 2.3 DESCRIPTION:Ensure that unauthorized software is either removed from use on enterprise assets or receives a documented exception. Review monthly, or more frequently.;TITLE:Utilize Automated Software Inventory Tools CONTROL:v8 2.4 DESCRIPTION:Utilize software inventory tools, when possible, throughout the enterprise to automate the discovery and documentation of installed software. ;TITLE:Centralize Access Control CONTROL:v8 6.7 DESCRIPTION:Centralize access control for all enterprise assets through a directory service or SSO provider, where supported.;TITLE:Address unapproved software CONTROL:v7 2.6 DESCRIPTION:Ensure that unauthorized software is either removed or the inventory is updated in a timely manner; | L30: 2.3 | M30: 2.4 | N30: 6.7 | O30: X | P30: X | Q30: X | R30: 2.6 | U30: X | V30: X | W30: X | X30: https://learn.microsoft.com/en-us/entra/identity/role-based-access-control/delegate-app-roles#restrict-who-can-create-applications:https://learn.microsoft.com/en-us/entra/identity-platform/how-applications-are-added#who-has-permission-to-add-applications-to-my-azure-ad-instance:https://learn.microsoft.com/en-us/security/benchmark/azure/mcsb-governance-strategy#gs-6-define-and-implement-identity-and-privileged-access-strategy:https://learn.microsoft.com/en-us/security/benchmark/azure/mcsb-privileged-access#pa-1-separate-and-limit-highly-privilegedadministrative-users:https://learn.microsoft.com/en-us/powershell/module/microsoft.graph.identity.signins/get-mgpolicyauthorizationpolicy?view=graph-powershell-1.0 | Y30: By default, `Users can register applications` is set to "Yes".
A31: 5 | B31: 5.15 | C31: Ensure that 'Guest users access restrictions' is set to 'Guest user access is restricted to properties and memberships of their own directory objects' | D31: Automated | E31: Limit guest user permissions. | F31: Limiting guest access ensures that guest accounts do not have permission for certain directory tasks, such as enumerating users, groups or other directory resources, and cannot be assigned to administrative roles in your directory. Guest access has three levels of restriction. 1. Guest users have the same access as members (most inclusive), 2. Guest users have limited access to properties and memberships of directory objects (default value), 3. Guest user access is restricted to properties and memberships of their own directory objects (most restrictive). The recommended option is the 3rd, most restrictive: "Guest user access is restricted to their own directory object". | G31: This may create additional requests for permissions to access resources that administrators will need to approve. According to https://learn.microsoft.com/en-us/entra/identity/users/users-restrict-guest-permissions#services-currently-not-supported Service without current support might have compatibility issues with the new guest restriction setting. - Forms - Project - Yammer - Planner in SharePoint | H31: **Remediate from Azure Portal** 1. From Azure Home select the Portal Menu 1. Select `Microsoft Entra ID` 1. Under `Manage`, select `External Identities` 1. Select `External collaboration settings` 1. Under `Guest user access`, set `Guest user access restrictions` to `Guest user access is restricted to properties and memberships of their own directory objects` 1. Click `Save` **Remediate from PowerShell** 1. Enter the following to update the policy ID: ``` Update-MgPolicyAuthorizationPolicy -GuestUserRoleId "2af84b1e-32c8-42b7-82bc-daa82404023b" ``` 2. Check the GuestUserRoleId again: ``` (Get-MgPolicyAuthorizationPolicy).GuestUserRoleId ``` 3. Ensure that the GuestUserRoleId is equal to the earlier entered value of `2af84b1e-32c8-42b7-82bc-daa82404023b`. | I31: **Audit from Azure Portal** 1. From Azure Home select the Portal Menu 1. Select `Microsoft Entra ID` 1. Under `Manage`, select `External Identities` 1. Select `External collaboration settings` 1. Under `Guest user access`, ensure that `Guest user access restrictions ` is set to `Guest user access is restricted to properties and memberships of their own directory objects` **Audit from PowerShell** Enter the following: ``` Connect-MgGraph (Get-MgPolicyAuthorizationPolicy).GuestUserRoleId ``` Which will give a result like: ``` Id : authorizationPolicy OdataType : Description : Used to manage authorization related settings across the company. DisplayName : Authorization Policy EnabledPreviewFeatures : {} GuestUserRoleId : 10dae51f-b6af-4016-8d66-8c2a99b929b3 PermissionGrantPolicyIdsAssignedToDefaultUserRole : {user-default-legacy} ``` If the GuestUserRoleID property does not equal `2af84b1e-32c8-42b7-82bc-daa82404023b` then it is not set to most restrictive. | K31: TITLE:Configure Data Access Control Lists CONTROL:v8 3.3 DESCRIPTION:Configure data access control lists based on a user’s need to know. Apply data access control lists, also known as access permissions, to local and remote file systems, databases, and applications.;TITLE:Define and Maintain Role-Based Access Control CONTROL:v8 6.8 DESCRIPTION:Define and maintain role-based access control, through determining and documenting the access rights necessary for each role within the enterprise to successfully carry out its assigned duties. Perform access control reviews of enterprise assets to validate that all privileges are authorized, on a recurring schedule at a minimum annually, or more frequently.;TITLE:Protect Information through Access Control Lists CONTROL:v7 14.6 DESCRIPTION:Protect all information stored on systems with file system, network share, claims, application, or database specific access control lists. These controls will enforce the principle that only authorized individuals should have access to the information based on their need to access the information as a part of their responsibilities.; | L31: 3.3 | M31: 6.8 | O31: X | P31: X | Q31: X | R31: 14.6 | U31: X | V31: X | W31: X | X31: https://learn.microsoft.com/en-us/entra/fundamentals/users-default-permissions#member-and-guest-users:https://learn.microsoft.com/en-us/security/benchmark/azure/mcsb-privileged-access#pa-3-manage-lifecycle-of-identities-and-entitlements:https://learn.microsoft.com/en-us/security/benchmark/azure/mcsb-governance-strategy#gs-2-define-and-implement-enterprise-segmentationseparation-of-duties-strategy:https://learn.microsoft.com/en-us/security/benchmark/azure/mcsb-governance-strategy#gs-6-define-and-implement-identity-and-privileged-access-strategy:https://learn.microsoft.com/en-us/entra/identity/users/users-restrict-guest-permissions | Y31: By default, `Guest user access restrictions` is set to `Guest users have limited access to properties and memberships of directory objects`.
A32: 5 | B32: 5.17 | C32: Ensure that 'Restrict access to Microsoft Entra admin center' is set to 'Yes' | D32: Manual | E32: Restrict access to the Microsoft Entra ID administration center to administrators only. **NOTE**: This only affects access to the Entra ID administrator's web portal. This setting does not prohibit privileged users from using other methods such as Rest API or Powershell to obtain sensitive information from Microsoft Entra ID. | F32: The Microsoft Entra ID administrative center has sensitive data and permission settings. All non-administrators should be prohibited from accessing any Microsoft Entra ID data in the administration center to avoid exposure. | G32: All administrative tasks will need to be done by Administrators, causing additional overhead in management of users and resources. | H32: **Remediate from Azure Portal** 1. From Azure Home select the Portal Menu 1. Select `Microsoft Entra ID` 1. Under `Manage`, select `Users` 1. Under `Manage`, select `User settings` 1. Under `Administration centre`, set `Restrict access to Microsoft Entra admin center` to `Yes` 1. Click `Save` | I32: **Audit from Azure Portal** 1. From Azure Home select the Portal Menu 1. Select `Microsoft Entra ID` 1. Under `Manage`, select `Users` 1. Under `Manage`, select `User settings` 1. Under `Administration centre`, ensure that `Restrict access to Microsoft Entra admin center` is set to `Yes` | K32: TITLE:Restrict Administrator Privileges to Dedicated Administrator Accounts CONTROL:v8 5.4 DESCRIPTION:Restrict administrator privileges to dedicated administrator accounts on enterprise assets. Conduct general computing activities, such as internet browsing, email, and productivity suite use, from the user’s primary, non-privileged account.;TITLE:Define and Maintain Role-Based Access Control CONTROL:v8 6.8 DESCRIPTION:Define and maintain role-based access control, through determining and documenting the access rights necessary for each role within the enterprise to successfully carry out its assigned duties. Perform access control reviews of enterprise assets to validate that all privileges are authorized, on a recurring schedule at a minimum annually, or more frequently.;TITLE:Ensure the Use of Dedicated Administrative Accounts CONTROL:v7 4.3 DESCRIPTION:Ensure that all users with administrative account access use a dedicated or secondary account for elevated activities. This account should only be used for administrative activities and not internet browsing, email, or similar activities.; | L32: 5.4 | M32: 6.8 | O32: X | P32: X | Q32: X | R32: 4.3 | U32: X | V32: X | W32: X | X32: https://learn.microsoft.com/en-us/entra/identity/role-based-access-control/permissions-reference:https://learn.microsoft.com/en-us/security/benchmark/azure/mcsb-governance-strategy#gs-2-define-and-implement-enterprise-segmentationseparation-of-duties-strategy:https://learn.microsoft.com/en-us/security/benchmark/azure/mcsb-governance-strategy#gs-6-define-and-implement-identity-and-privileged-access-strategy:https://learn.microsoft.com/en-us/security/benchmark/azure/mcsb-privileged-access#pa-1-separate-and-limit-highly-privilegedadministrative-users | Y32: By default, `Restrict access to Microsoft Entra admin center` is set to `No`
A33: 5 | B33: 5.22 | C33: Ensure that 'Require Multifactor Authentication to register or join devices with Microsoft Entra' is set to 'Yes' | D33: Manual | E33: **NOTE:** This recommendation is only relevant if your subscription is using Per-User MFA. If your organization is licensed to use Conditional Access, the preferred method of requiring MFA to join devices to Entra ID is to use a Conditional Access policy (see additional information below for link). Joining or registering devices to Microsoft Entra ID should require multi-factor authentication. | F33: Multi-factor authentication is recommended when adding devices to Microsoft Entra ID. When set to `Yes`, users who are adding devices from the internet must first use the second method of authentication before their device is successfully added to the directory. This ensures that rogue devices are not added to the domain using a compromised user account. | G33: A slight impact of additional overhead, as Administrators will now have to approve every access to the domain. | H33: **Remediate from Azure Portal** 1. From Azure Home select the Portal Menu 1. Select `Microsoft Entra ID` 1. Under `Manage`, select `Devices` 1. Under `Manage`, select `Device settings` 1. Under `Microsoft Entra join and registration settings`, set `Require Multifactor Authentication to register or join devices with Microsoft Entra` to `Yes` 1. Click `Save` | I33: **Audit from Azure Portal** 1. From Azure Home select the Portal Menu 1. Select `Microsoft Entra ID` 1. Under `Manage`, select `Devices` 1. Under `Manage`, select `Device settings` 1. Under `Microsoft Entra join and registration settings`, ensure that `Require Multifactor Authentication to register or join devices with Microsoft Entra` is set to `Yes` | J33: If Conditional Access is available, this recommendation should be bypassed in favor of the Conditional Access implementation of requiring Multifactor Authentication to register or join devices with Microsoft Entra. https://learn.microsoft.com/en-us/entra/identity/conditional-access/policy-all-users-device-registration | K33: TITLE:Require MFA for Externally-Exposed Applications CONTROL:v8 6.3 DESCRIPTION:Require all externally-exposed enterprise or third-party applications to enforce MFA, where supported. Enforcing MFA through a directory service or SSO provider is a satisfactory implementation of this Safeguard.;TITLE:Require MFA for Remote Network Access CONTROL:v8 6.4 DESCRIPTION:Require MFA for remote network access.;TITLE:Require Multi-factor Authentication CONTROL:v7 16.3 DESCRIPTION:Require multi-factor authentication for all user accounts, on all systems, whether managed onsite or by a third-party provider.; | L33: 6.3 | M33: 6.4 | O33: X | P33: X | Q33: X | R33: 16.3 | V33: X | W33: X | X33: https://learn.microsoft.com/en-us/entra/identity/conditional-access/policy-all-users-device-registration:https://learn.microsoft.com/en-us/security/benchmark/azure/mcsb-identity-management#im-6-use-strong-authentication-controls | Y33: By default, `Require Multifactor Authentication to register or join devices with Microsoft Entra` is set to `No`.
A34: 5 | B34: 5.23 | C34: Ensure that no custom subscription administrator roles exist | D34: Automated | E34: The principle of least privilege should be followed and only necessary privileges should be assigned instead of allowing full administrative access. | F34: Custom roles in Azure with administrative access can obfuscate the permissions granted and introduce complexity and blind spots to the management of privileged identities. For less mature security programs without regular identity audits, the creation of Custom roles should be avoided entirely. For more mature security programs with regular identity audits, Custom Roles should be audited for use and assignment, used minimally, and the principle of least privilege should be observed when granting permissions | G34: Subscriptions will need to be handled by Administrators with permissions. | H34: **Remediate from Azure Portal** 1. From Azure Home select the Portal Menu. 1. Select `Subscriptions`. 1. Select a subscription. 1. Select `Access control (IAM)`. 1. Select `Roles`. 1. Click `Type` and select `Custom role` from the drop-down menu. 1. Check the box next to each role which grants subscription administrator privileges. 1. Select `Delete`. 1. Select `Yes`. **Remediate from Azure CLI** List custom roles: ``` az role definition list --custom-role-only True ``` Check for entries with `assignableScope` of the `subscription`, and an action of `*`. To remove a violating role: ``` az role definition delete --name <role name> ``` Note that any role assignments must be removed before a custom role can be deleted. Ensure impact is assessed before deleting a custom role granting subscription administrator privileges. | I34: **Audit from Azure Portal** 1. From Azure Home select the Portal Menu. 1. Select `Subscriptions`. 1. Select a subscription. 1. Select `Access control (IAM)`. 1. Select `Roles`. 1. Click `Type` and select `Custom role` from the drop-down menu. 1. Select `View` next to a role. 1. Select `JSON`. 1. Check for `assignableScopes` set to the subscription, and `actions` set to `*`. 1. Repeat steps 7-9 for each custom role. **Audit from Azure CLI** List custom roles: ``` az role definition list --custom-role-only True ``` Check for entries with `assignableScope` of the `subscription`, and an action of `*` **Audit from PowerShell** ``` Connect-AzAccount Get-AzRoleDefinition |Where-Object {($_.IsCustom -eq $true) -and ($_.Actions.contains('*'))} ``` Check the output for `AssignableScopes` value set to the subscription. **Audit from Azure Policy** If referencing a digital copy of this Benchmark, clicking a Policy ID will open a link to the associated Policy definition in Azure. If referencing a printed copy, you can search Policy IDs from this URL: https://portal.azure.com/#view/Microsoft_Azure_Policy/PolicyMenuBlade/~/Definitions - **Policy ID:** [a451c1ef-c6ca-483d-87ed-f49761e3ffb5](https://portal.azure.com/#view/Microsoft_Azure_Policy/PolicyDetailBlade/definitionId/%2Fproviders%2FMicrosoft.Authorization%2FpolicyDefinitions%2Fa451c1ef-c6ca-483d-87ed-f49761e3ffb5) **- Name:** 'Audit usage of custom RBAC roles' | K34: TITLE:Restrict Administrator Privileges to Dedicated Administrator Accounts CONTROL:v8 5.4 DESCRIPTION:Restrict administrator privileges to dedicated administrator accounts on enterprise assets. Conduct general computing activities, such as internet browsing, email, and productivity suite use, from the user’s primary, non-privileged account.;TITLE:Define and Maintain Role-Based Access Control CONTROL:v8 6.8 DESCRIPTION:Define and maintain role-based access control, through determining and documenting the access rights necessary for each role within the enterprise to successfully carry out its assigned duties. Perform access control reviews of enterprise assets to validate that all privileges are authorized, on a recurring schedule at a minimum annually, or more frequently.;TITLE:Maintain Inventory of Administrative Accounts CONTROL:v7 4.1 DESCRIPTION:Use automated tools to inventory all administrative accounts, including domain and local accounts, to ensure that only authorized individuals have elevated privileges.; | L34: 5.4 | M34: 6.8 | O34: X | P34: X | Q34: X | R34: 4.1 | V34: X | W34: X | X34: https://learn.microsoft.com/en-us/azure/cost-management-billing/manage/add-change-subscription-administrator:https://learn.microsoft.com/en-us/security/benchmark/azure/mcsb-privileged-access#pa-1-separate-and-limit-highly-privilegedadministrative-users:https://learn.microsoft.com/en-us/security/benchmark/azure/mcsb-privileged-access#pa-3-manage-lifecycle-of-identities-and-entitlements:https://learn.microsoft.com/en-us/security/benchmark/azure/mcsb-governance-strategy#gs-2-define-and-implement-enterprise-segmentationseparation-of-duties-strategy:https://learn.microsoft.com/en-us/security/benchmark/azure/mcsb-governance-strategy#gs-6-define-and-implement-identity-and-privileged-access-strategy:https://learn.microsoft.com/en-us/security/benchmark/azure/mcsb-privileged-access#pa-7-follow-just-enough-administration-least-privilege-principle | Y34: By default, no custom owner roles are created.
A35: 5 | B35: 5.26 | C35: Ensure fewer than 5 users have global administrator assignment | D35: Manual | E35: This recommendation aims to maintain a balance between security and operational efficiency by ensuring that a minimum of 2 and a maximum of 4 users are assigned the Global Administrator role in Microsoft Entra ID. Having at least two Global Administrators ensures redundancy, while limiting the number to four reduces the risk of excessive privileged access. | F35: The Global Administrator role has extensive privileges across all services in Microsoft Entra ID. The Global Administrator role should never be used in regular daily activities; administrators should have a regular user account for daily activities, and a separate account for administrative responsibilities. Limiting the number of Global Administrators helps mitigate the risk of unauthorized access, reduces the potential impact of human error, and aligns with the principle of least privilege to reduce the attack surface of an Azure tenant. Conversely, having at least two Global Administrators ensures that administrative functions can be performed without interruption in case of unavailability of a single admin. For any accounts assigned the Global Administrator role, at least one strong authentication method such as a FIDO2 key or certificate is strongly advised. Additional detail on strong passwordless authentication methods is provided in the recommendation titled "Ensure passwordless authentication methods are considered" and a link can be found in references for more detail about emergency access accounts. | G35: Implementing this recommendation may require changes in administrative workflows or the redistribution of roles and responsibilities. Adequate training and awareness should be provided to all Global Administrators. NOTE: If an organization's tenant is using a third-party identity provider, the audit and remediation procedures presented here may not be relevant. The principle of the recommendation is still relevant, and compensating controls that are relevant to the third-party identity provider should be implemented. | H35: **Remediate from Azure Portal** 1. From Azure Home select the Portal Menu 1. Select `Microsoft Entra ID` 1. Under `Manage`, select `Roles and administrators` 1. Under `Administrative Roles`, select `Global Administrator` If more than 4 users are assigned: 1. Remove Global Administrator role for users which do not or no longer require the role. 1. Assign Global Administrator role via PIM which can be activated when required. 1. Assign more granular roles to users to conduct their duties. If only one user is assigned: 1. Provide the Global Administrator role to a trusted user or create a break glass admin account. | I35: **Audit from Azure Portal** 1. From Azure Home select the Portal Menu 1. Select `Microsoft Entra ID` 1. Under `Manage`, select `Roles and administrators` 1. Under `Administrative Roles`, select `Global Administrator` 1. Ensure less than 5 users are actively assigned the role. 1. Ensure that at least 2 users are actively assigned the role. | K35: TITLE:Establish and Maintain an Inventory of Accounts CONTROL:v8 5.1 DESCRIPTION:Establish and maintain an inventory of all accounts managed in the enterprise. The inventory must include both user and administrator accounts. The inventory, at a minimum, should contain the person’s name, username, start/stop dates, and department. Validate that all active accounts are authorized, on a recurring schedule at a minimum quarterly, or more frequently.;TITLE:Maintain Inventory of Administrative Accounts CONTROL:v7 4.1 DESCRIPTION:Use automated tools to inventory all administrative accounts, including domain and local accounts, to ensure that only authorized individuals have elevated privileges.; | L35: 5.1 | O35: X | P35: X | Q35: X | R35: 4.1 | V35: X | W35: X | X35: https://learn.microsoft.com/en-us/entra/identity/role-based-access-control/best-practices#5-limit-the-number-of-global-administrators-to-less-than-5:https://learn.microsoft.com/en-us/microsoft-365/admin/add-users/about-admin-roles?view=o365-worldwide#security-guidelines-for-assigning-roles:https://learn.microsoft.com/en-us/entra/identity/role-based-access-control/security-emergency-access:https://learn.microsoft.com/en-us/security/benchmark/azure/mcsb-privileged-access#pa-1-separate-and-limit-highly-privilegedadministrative-users
A36: 5 | B36: 5.27 | C36: Ensure there are between 2 and 3 subscription owners | D36: Automated | E36: The Owner role in Azure grants full control over all resources in a subscription, including the ability to assign roles to others. | F36: Limit the number of security principals (users, groups, service principals, and managed identities) assigned the Owner role to between 2 and 3. If groups are used, ensure their membership is tightly controlled and regularly reviewed to avoid privilege sprawl. | G36: Implementation may require changes in administrative workflows or the redistribution of roles and responsibilities. The recommendation to have between 2 and 3 Owners per subscription must account for all security principals that can be assigned the Owner role, not just individual users. This includes: - User accounts - Entra ID groups - Service principals (used by applications or automation) - Managed identities (system-assigned or user-assigned) | H36: **Remediate from Azure Portal** 1. Go to `Subscriptions`. 1. Click the name of a subscription. 1. Click `Access Controls (IAM)`. 1. Click `Role assignments`. 1. Click `Role : All`. 1. Click the arrow next to `All`. 1. Click `Owner`. 1. Check the box next to members from whom the owner role should be removed. 1. Click `Delete`. 1. Click `Yes`. 1. Repeat steps 1-10 for each subscription requiring remediation. **Remediate from Azure CLI** Run the following command to delete role assignments by role assignment id: ``` az role assignment delete --ids <role-assignment-ids> ``` | I36: **Audit from Azure Portal** 1. Go to `Subscriptions`. 1. Click the name of a subscription. 1. Click `Access Controls (IAM)`. 1. Click `Role assignments`. 1. Click `Role : All`. 1. Click the arrow next to `All`. 1. Click `Owner`. 1. Ensure a minimum of 2 and a maximum of 3 members are returned. 1. Repeat steps 1-8 for each subscription. **Audit from Azure CLI** Run the following command to list members with role `Owner` at a given subscription scope: ``` az role assignment list --role Owner --scope /subscriptions/<subscription-id> --query "[].{PrincipalName:principalName, Type:principalType}" ``` Ensure a minimum of 2 and a maximum of 3 members are returned. For each Owner assignment, check: If principalType == Group, review group membership. If principalType == ServicePrincipal or ManagedIdentity, validate necessity and scope. Repeat for each subscription. **Audit from PowerShell** Run the following command to list members with role `Owner` at a given subscription scope: ``` Get-AzRoleAssignment -RoleDefinitionName Owner -Scope /subscriptions/<subscription-id> ``` Ensure a minimum of 2 and a maximum of 3 members are returned. Repeat for each subscription. **Audit from Azure Policy** If referencing a digital copy of this Benchmark, clicking a Policy ID will open a link to the associated Policy definition in Azure. If referencing a printed copy, you can search Policy IDs from this URL: https://portal.azure.com/#view/Microsoft_Azure_Policy/PolicyMenuBlade/~/Definitions - **Policy ID:** [09024ccc-0c5f-475e-9457-b7c0d9ed487b](https://portal.azure.com/#view/Microsoft_Azure_Policy/PolicyDetailBlade/definitionId/%2Fproviders%2FMicrosoft.Authorization%2FpolicyDefinitions%2F09024ccc-0c5f-475e-9457-b7c0d9ed487b) **- Name:** 'There should be more than one owner assigned to your subscription' - **Policy ID:** [4f11b553-d42e-4e3a-89be-32ca364cad4c](https://portal.azure.com/#view/Microsoft_Azure_Policy/PolicyDetailBlade/definitionId/%2Fproviders%2FMicrosoft.Authorization%2FpolicyDefinitions%2F4f11b553-d42e-4e3a-89be-32ca364cad4c) **- Name:** 'A maximum of 3 owners should be designated for your subscription' | K36: TITLE:Establish and Maintain an Inventory of Accounts CONTROL:v8 5.1 DESCRIPTION:Establish and maintain an inventory of all accounts managed in the enterprise. The inventory must include both user and administrator accounts. The inventory, at a minimum, should contain the person’s name, username, start/stop dates, and department. Validate that all active accounts are authorized, on a recurring schedule at a minimum quarterly, or more frequently.;TITLE:Maintain Inventory of Administrative Accounts CONTROL:v7 4.1 DESCRIPTION:Use automated tools to inventory all administrative accounts, including domain and local accounts, to ensure that only authorized individuals have elevated privileges.; | L36: 5.1 | O36: X | P36: X | Q36: X | R36: 4.1 | V36: X | W36: X | X36: https://learn.microsoft.com/en-us/cli/azure/role/assignment:https://learn.microsoft.com/en-us/powershell/module/az.resources/get-azroleassignment:https://learn.microsoft.com/en-us/azure/role-based-access-control/built-in-roles/privileged#owner:https://learn.microsoft.com/en-us/azure/role-based-access-control/role-assignments-portal-subscription-admin | Y36: A subscription has 1 owner by default.
A37: 5.1 | C37: Security Defaults (Per-User MFA) | E37: **IMPORTANT: READ BELOW BEFORE PROCEEDING!** ----- - If your organization pays for Microsoft Entra ID licensing (included in Microsoft 365 E3, E5, F5, or Business Premium, and EM&S E3 or E5 licenses) and **CAN** use Conditional Access, ignore the recommendations in this section and proceed to the Conditional Access section. - If your organization is using the free tier of Entra ID (Office 365 E1, E3, or E5, and Microsoft 365 F1 or F3 licenses) and **CAN NOT** use Conditional Access, proceed with the Security Defaults guidance in this section, and ignore the recommendations in the Conditional Access section. Conditional Access is preferred, but Security Defaults (Per-User MFA) is recommended only if Conditional Access isn't available. Why is this **IMPORTANT**? The Azure "Security Defaults" recommendations represent an entry-level set of recommendations (such as Multi-Factor Authentication) which will be relevant to organizations and tenants that are either just starting to use Azure, or are only utilizing a bare minimum feature set, and rely on the free license tier of Microsoft Entra ID. Security Defaults recommendations are intended to ensure that these use cases are still capable of establishing a strong baseline of secure configuration. **If your subscription is licensed to use Microsoft Entra ID P1 or P2, it is strongly recommended that the "Security Defaults" section (this section and the recommendations therein) be bypassed in favor of the use of "Conditional Access."** ----- **IMPORTANT: READ ABOVE BEFORE PROCEEDING!**
A38: 5.1 | B38: 5.1.1 | C38: Ensure that 'security defaults' is enabled in Microsoft Entra ID | D38: Automated | E38: [**IMPORTANT - Please read the section overview:** If your organization pays for Microsoft Entra ID licensing (included in Microsoft 365 E3, E5, F5, or Business Premium, and EM&S E3 or E5 licenses) and **CAN** use Conditional Access, ignore the recommendations in this section and proceed to the Conditional Access section.] Security defaults in Microsoft Entra ID make it easier to be secure and help protect your organization. Security defaults contain preconfigured security settings for common attacks. Security defaults is available to everyone. The goal is to ensure that all organizations have a basic level of security enabled at no extra cost. You may turn on security defaults in the Azure portal. | F38: Security defaults provide secure default settings that we manage on behalf of organizations to keep customers safe until they are ready to manage their own identity security settings. For example, doing the following: - Requiring all users and admins to register for MFA. - Challenging users with MFA - when necessary, based on factors such as location, device, role, and task. - Disabling authentication from legacy authentication clients, which can’t do MFA. | G38: This recommendation should be implemented initially and then may be overridden by other service/product specific CIS Benchmarks. Administrators should also be aware that certain configurations in Microsoft Entra ID may impact other Microsoft services such as Microsoft 365. | H38: **Remediate from Azure Portal** To enable security defaults in your directory: 1. From Azure Home select the Portal Menu. 1. Browse to `Microsoft Entra ID` > `Properties`. 1. Select `Manage security defaults`. 1. Under `Security defaults`, select `Enabled (recommended)`. 1. Select `Save`. **Remediate from Powershell** ``` Connect-MgGraph -Scopes "Policy.ReadWrite.ApplicationConfiguration" Update-MgPolicyIdentitySecurityDefaultEnforcementPolicy -IsEnabled $true (Get-MgPolicyIdentitySecurityDefaultEnforcementPolicy).IsEnabled ``` **Remediate from Azure CLI** ``` az rest --method patch --url 'https://graph.microsoft.com/v1.0/policies/identitySecurityDefaultsEnforcementPolicy' --body '{"isEnabled":true}' az rest --method get --url 'https://graph.microsoft.com/v1.0/policies/identitySecurityDefaultsEnforcementPolicy' --query "isEnabled" ``` | I38: **Audit from Azure Portal** To ensure security defaults is enabled in your directory: 1. From Azure Home select the Portal Menu. 2. Browse to `Microsoft Entra ID` > `Properties`. 3. Select `Manage security defaults`. 4. Under `Security defaults`, verify that `Enabled (recommended)` is selected. **Audit from Powershell** ``` Connect-MgGraph -Scopes "Policy.Read.All" (Get-MgPolicyIdentitySecurityDefaultEnforcementPolicy).IsEnabled ``` Returned value should be `true`. **Audit from Azure CLI** ``` az login az rest --method get --url 'https://graph.microsoft.com/v1.0/policies/identitySecurityDefaultsEnforcementPolicy' --query "isEnabled" ``` Returned value should be `true`. | J38: This recommendation differs from the [Microsoft 365 Benchmark](https://workbench.cisecurity.org/benchmarks/5741). This is because the potential impact associated with disabling Security Defaults is dependent upon the security settings implemented in the environment. It is recommended that organizations disabling Security Defaults implement appropriate security settings to replace the settings configured by Security Defaults. | K38: TITLE:Establish and Maintain a Secure Configuration Process CONTROL:v8 4.1 DESCRIPTION:Establish and maintain a secure configuration process for enterprise assets (end-user devices, including portable and mobile, non-computing/IoT devices, and servers) and software (operating systems and applications). Review and update documentation annually, or when significant enterprise changes occur that could impact this Safeguard.;TITLE:Establish Secure Configurations CONTROL:v7 5.1 DESCRIPTION:Maintain documented, standard security configuration standards for all authorized operating systems and software.; | L38: 4.1 | O38: X | P38: X | Q38: X | R38: 5.1 | U38: X | V38: X | W38: X | X38: https://learn.microsoft.com/en-us/entra/fundamentals/security-defaults:https://techcommunity.microsoft.com/t5/azure-active-directory-identity/introducing-security-defaults/ba-p/1061414:https://learn.microsoft.com/en-us/security/benchmark/azure/mcsb-identity-management#im-2-protect-identity-and-authentication-systems | Y38: If your tenant was created on or after October 22, 2019, security defaults may already be enabled in your tenant.
A39: 5.1 | B39: 5.1.2 | C39: Ensure that 'multifactor authentication' is 'enabled' for all users | D39: Automated | E39: [**IMPORTANT - Please read the section overview:** If your organization pays for Microsoft Entra ID licensing (included in Microsoft 365 E3, E5, F5, or Business Premium, and EM&S E3 or E5 licenses) and **CAN** use Conditional Access, ignore the recommendations in this section and proceed to the Conditional Access section.] Enable multifactor authentication for all users. **Note:** Since 2024, Azure has been rolling out mandatory multifactor authentication. For more information: - https://azure.microsoft.com/en-us/blog/announcing-mandatory-multi-factor-authentication-for-azure-sign-in - https://learn.microsoft.com/en-us/entra/identity/authentication/concept-mandatory-multifactor-authentication | F39: Multifactor authentication requires an individual to present a minimum of two separate forms of authentication before access is granted. Multifactor authentication provides additional assurance that the individual attempting to gain access is who they claim to be. With multifactor authentication, an attacker would need to compromise at least two different authentication mechanisms, increasing the difficulty of compromise and thus reducing the risk. | G39: Users would require two forms of authentication before any access is granted. Additional administrative time will be required for managing dual forms of authentication when enabling multifactor authentication. | H39: **Remediate from Azure Portal** 1. Go to `Microsoft Entra ID`. 1. Under `Manage`, click `Users`. 1. Click `Per-user MFA` from the top menu. 1. Click the box next to a user with `Status` `disabled`. 1. Click `Enable MFA`. 1. Click `Enable`. 1. Repeat steps 1-6 for each user requiring remediation. **Other options within Azure Portal** - [https://learn.microsoft.com/en-us/entra/identity/authentication/tutorial-enable-azure-mfa](https://learn.microsoft.com/en-us/entra/identity/authentication/tutorial-enable-azure-mfa) - [https://learn.microsoft.com/en-us/entra/identity/authentication/howto-mfa-mfasettings](https://learn.microsoft.com/en-us/entra/identity/authentication/howto-mfa-mfasettings) - [https://learn.microsoft.com/en-us/entra/identity/conditional-access/policy-old-require-mfa-admin](https://learn.microsoft.com/en-us/entra/identity/conditional-access/policy-old-require-mfa-admin) - [https://learn.microsoft.com/en-us/entra/identity/authentication/howto-mfa-getstarted#enable-multi-factor-authentication-with-conditional-access](https://learn.microsoft.com/en-us/entra/identity/authentication/howto-mfa-getstarted#enable-multi-factor-authentication-with-conditional-access) | I39: **Audit from Azure Portal** 1. Go to `Microsoft Entra ID`. 1. Under `Manage`, click `Users`. 1. Click `Per-user MFA` from the top menu. 1. Ensure that `Status` is `enabled` for all users. **Audit from PowerShell** Run the following Graph PowerShell command: ``` get-mguser -All | where {$_.StrongAuthenticationMethods.Count -eq 0} | Select-Object -Property UserPrincipalName ``` If the output contains any `UserPrincipalName`, then this recommendation is non-compliant. | K39: TITLE:Require MFA for Externally-Exposed Applications CONTROL:v8 6.3 DESCRIPTION:Require all externally-exposed enterprise or third-party applications to enforce MFA, where supported. Enforcing MFA through a directory service or SSO provider is a satisfactory implementation of this Safeguard.;TITLE:Require MFA for Remote Network Access CONTROL:v8 6.4 DESCRIPTION:Require MFA for remote network access.;TITLE:Require Multi-factor Authentication CONTROL:v7 16.3 DESCRIPTION:Require multi-factor authentication for all user accounts, on all systems, whether managed onsite or by a third-party provider.; | L39: 6.3 | M39: 6.4 | O39: X | P39: X | Q39: X | R39: 16.3 | V39: X | W39: X | X39: https://learn.microsoft.com/en-us/entra/identity/authentication/concept-mfa-howitworks:https://learn.microsoft.com/en-us/entra/identity/authentication/concept-mandatory-multifactor-authentication:https://azure.microsoft.com/en-us/blog/announcing-mandatory-multi-factor-authentication-for-azure-sign-in/:https://learn.microsoft.com/en-us/security/benchmark/azure/mcsb-identity-management#im-4-authenticate-server-and-services | Y39: Multifactor authentication is not enabled for all users by default. Starting in 2024, multifactor authentication is enabled for administrative accounts by default.
A40: 5.1 | B40: 5.1.3 | C40: Ensure that 'Allow users to remember multifactor authentication on devices they trust' is disabled | D40: Manual | E40: [**IMPORTANT - Please read the section overview:** If your organization pays for Microsoft Entra ID licensing (included in Microsoft 365 E3, E5, F5, or Business Premium, and EM&S E3 or E5 licenses) and **CAN** use Conditional Access, ignore the recommendations in this section and proceed to the Conditional Access section.] Do not allow users to remember multi-factor authentication on devices. | F40: Remembering Multi-Factor Authentication (MFA) for devices and browsers allows users to have the option to bypass MFA for a set number of days after performing a successful sign-in using MFA. This can enhance usability by minimizing the number of times a user may need to perform two-step verification on the same device. However, if an account or device is compromised, remembering MFA for trusted devices may affect security. Hence, it is recommended that users not be allowed to bypass MFA. | G40: For every login attempt, the user will be required to perform multi-factor authentication. | H40: **Remediate from Azure Portal** 1. From Azure Home select the Portal Menu 1. Select `Microsoft Entra ID` 1. Under `Manage`, click `Users` 1. Click the `Per-user MFA` button on the top bar 1. Click on `Service settings` 1. Uncheck the box next to `Allow users to remember multi-factor authentication on devices they trust` 1. Click `Save` | I40: **Audit from Azure Portal** 1. From Azure Home select the Portal Menu 1. Select `Microsoft Entra ID` 1. Under `Manage`, click `Users` 1. Click the `Per-user MFA` button on the top bar 1. Click on `Service settings` 1. Ensure that `Allow users to remember multi-factor authentication on devices they trust` is not enabled | K40: TITLE:Require MFA for Externally-Exposed Applications CONTROL:v8 6.3 DESCRIPTION:Require all externally-exposed enterprise or third-party applications to enforce MFA, where supported. Enforcing MFA through a directory service or SSO provider is a satisfactory implementation of this Safeguard.;TITLE:Require MFA for Remote Network Access CONTROL:v8 6.4 DESCRIPTION:Require MFA for remote network access.;TITLE:Require Multi-factor Authentication CONTROL:v7 16.3 DESCRIPTION:Require multi-factor authentication for all user accounts, on all systems, whether managed onsite or by a third-party provider.; | L40: 6.3 | M40: 6.4 | O40: X | P40: X | Q40: X | R40: 16.3 | V40: X | W40: X | X40: https://learn.microsoft.com/en-us/entra/identity/authentication/howto-mfa-mfasettings#remember-multi-factor-authentication-for-devices-that-users-trust:https://learn.microsoft.com/en-us/security/benchmark/azure/security-controls-v3-identity-management#im-4-use-strong-authentication-controls-for-all-azure-active-directory-based-access:https://learn.microsoft.com/en-us/security/benchmark/azure/mcsb-identity-management#im-6-use-strong-authentication-controls | Y40: By default, `Allow users to remember multi-factor authentication on devices they trust` is disabled.
A41: 5.2 | C41: Conditional Access | E41: For most Azure tenants, and certainly for organizations with a significant use of Microsoft Entra ID, Conditional Access policies are recommended and preferred. To use Conditional Access Policies, a licensing plan is required, and **Security Defaults must be disabled**. Because of the licensing requirement, all Conditional Access policies are assigned a profile of "Level 2." Conditional Access requires one of the following plans: - Microsoft Entra ID P1 or P2 - Microsoft 365 Business Premium - Microsoft 365 E3 or E5 - Microsoft 365 F1, F3, F5 Security and F5 Security + Compliance - Enterprise Mobility & Security E3 or E5
A42: 5.3 | C42: Periodic Identity Reviews | E42: Security Best Practices for Identity services should include operational reviews that periodically ensure the integrity and necessity of accounts and permissions. These operational practices should be performed regularly on a cadence that is based on your organization's policy or compliance requirements. **NOTE:** The recommendations in this section may not have a precise audit or remediation procedure because they may not be a configurable setting as much as they are an operative task that should be performed on a periodic basis.
A43: 5.3 | B43: 5.3.1 | C43: Ensure that Azure admin accounts are not used for daily operations | D43: Manual | E43: Microsoft Azure admin accounts should not be used for routine, non-administrative tasks. | F43: Using admin accounts for daily operations increases the risk of accidental misconfigurations and security breaches. | G43: Minor administrative overhead includes managing separate accounts, enforcing stricter access controls, and potential licensing costs for advanced security features. | H43: If admin accounts are being used for daily operations, consider the following: - Monitor and alert on unusual activity. - Enforce the principle of least privilege. - Revoke any unnecessary administrative access. - Use Conditional Access to limit access to resources. - Ensure that administrators have separate admin and user accounts. - Use Microsoft Entra ID Protection to detect, investigate, and remediate identity-based risks. - Use Privileged Identity Management (PIM) in Microsoft Entra ID to limit standing administrator access to privileged roles, discover who has access, and review privileged access. | I43: **Audit from Azure Portal** Monitor: 1. Go to `Monitor`. 1. Click `Activity log`. 1. Review the activity log and ensure that admin accounts are not being used for daily operations. Microsoft Entra ID: 1. Go to `Microsoft Entra ID`. 1. Under `Monitoring`, click `Sign-in logs`. 1. Review the sign-in logs and ensure that admin accounts are not being accessed more frequently than necessary. | K43: TITLE:Restrict Administrator Privileges to Dedicated Administrator Accounts CONTROL:v8 5.4 DESCRIPTION:Restrict administrator privileges to dedicated administrator accounts on enterprise assets. Conduct general computing activities, such as internet browsing, email, and productivity suite use, from the user’s primary, non-privileged account.;TITLE:Ensure the Use of Dedicated Administrative Accounts CONTROL:v7 4.3 DESCRIPTION:Ensure that all users with administrative account access use a dedicated or secondary account for elevated activities. This account should only be used for administrative activities and not internet browsing, email, or similar activities.; | L43: 5.4 | O43: X | P43: X | Q43: X | R43: 4.3 | U43: X | V43: X | W43: X | X43: https://learn.microsoft.com/en-us/security/privileged-access-workstations/critical-impact-accounts
A44: 5.3 | B44: 5.3.2 | C44: Ensure that guest users are reviewed on a regular basis | D44: Manual | E44: Microsoft Entra ID has native and extended identity functionality allowing you to invite people from outside your organization to be guest users in your cloud account and sign in with their own work, school, or social identities. While an automated assessment procedure exists for this recommendation, the assessment status remains manual. Evaluating the appropriateness of guest users requires a manual review, as it depends on the specific needs and context of each organization and environment. | F44: Guest users are typically added outside your employee on-boarding/off-boarding process and could potentially be overlooked indefinitely. To prevent this, guest users should be reviewed on a regular basis. During this audit, guest users should also be determined to not have administrative privileges. | G44: Before removing guest users, determine their use and scope. Like removing any user, there may be unforeseen consequences to systems if an account is removed without careful consideration. | H44: **Remediate from Azure Portal** 1. From Azure Home select the Portal Menu 1. Select `Microsoft Entra ID` 1. Under `Manage`, select `Users` 1. Click on `Add filter` 1. Select `User type` 1. Select `Guest` from the Value dropdown 1. Click `Apply` 1. Check the box next to all `Guest` users that are no longer required or are inactive 1. Click `Delete` 1. Click `OK` **Remediate from Azure CLI** Before deleting the user, set it to inactive using the ID from the Audit Procedure to determine if there are any dependent systems. ``` az ad user update --id <exampleaccountid@domain.com> --account-enabled {false} ``` After determining that there are no dependent systems, delete the user. ``` Remove-AzureADUser -ObjectId <exampleaccountid@domain.com> ``` **Remediate from Azure PowerShell** Before deleting the user, set it to inactive using the ID from the Audit Procedure to determine if there are any dependent systems. ``` Set-AzureADUser -ObjectId "<exampleaccountid@domain.com>" -AccountEnabled false ``` After determining that there are no dependent systems, delete the user. ``` PS C:\>Remove-AzureADUser -ObjectId <exampleaccountid@domain.com> ``` | I44: **Audit from Azure Portal** 1. From Azure Home select the Portal Menu 1. Select `Microsoft Entra ID` 1. Under `Manage`, select `Users` 1. Click on `Add filter` 1. Select `User type` 1. Select `Guest` from the Value dropdown 1. Click `Apply` 1. Audit the listed guest users **Audit from Azure CLI** ``` az ad user list --query "[?userType=='Guest']" ``` Ensure all users listed are still required and not inactive. **Audit from Azure PowerShell** ``` Get-AzureADUser |Where-Object {$_.UserType -like "Guest"} |Select-Object DisplayName, UserPrincipalName, UserType -Unique ``` **Audit from Azure Policy** If referencing a digital copy of this Benchmark, clicking a Policy ID will open a link to the associated Policy definition in Azure. If referencing a printed copy, you can search Policy IDs from this URL: https://portal.azure.com/#view/Microsoft_Azure_Policy/PolicyMenuBlade/~/Definitions - **Policy ID:** [e9ac8f8e-ce22-4355-8f04-99b911d6be52](https://portal.azure.com/#view/Microsoft_Azure_Policy/PolicyDetailBlade/definitionId/%2Fproviders%2FMicrosoft.Authorization%2FpolicyDefinitions%2Fe9ac8f8e-ce22-4355-8f04-99b911d6be52) **- Name:** 'Guest accounts with read permissions on Azure resources should be removed' - **Policy ID:** [94e1c2ac-cbbe-4cac-a2b5-389c812dee87](https://portal.azure.com/#view/Microsoft_Azure_Policy/PolicyDetailBlade/definitionId/%2Fproviders%2FMicrosoft.Authorization%2FpolicyDefinitions%2F94e1c2ac-cbbe-4cac-a2b5-389c812dee87) **- Name:** 'Guest accounts with write permissions on Azure resources should be removed' - **Policy ID:** [339353f6-2387-4a45-abe4-7f529d121046](https://portal.azure.com/#view/Microsoft_Azure_Policy/PolicyDetailBlade/definitionId/%2Fproviders%2FMicrosoft.Authorization%2FpolicyDefinitions%2F339353f6-2387-4a45-abe4-7f529d121046) **- Name:** 'Guest accounts with owner permissions on Azure resources should be removed' | J44: It is good practice to use a dynamic security group to manage guest users. To create the dynamic security group: 1. Navigate to the 'Microsoft Entra ID' blade in the Azure Portal 2. Select the 'Groups' item 3. Create new 4. Type of 'dynamic' 5. Use the following dynamic selection rule. "(user.userType -eq "Guest")" 6. Once the group has been created, select access reviews option and create a new access review with a period of monthly and send to relevant administrators for review. | K44: TITLE:Establish and Maintain an Inventory of Accounts CONTROL:v8 5.1 DESCRIPTION:Establish and maintain an inventory of all accounts managed in the enterprise. The inventory must include both user and administrator accounts. The inventory, at a minimum, should contain the person’s name, username, start/stop dates, and department. Validate that all active accounts are authorized, on a recurring schedule at a minimum quarterly, or more frequently.;TITLE:Disable Dormant Accounts CONTROL:v8 5.3 DESCRIPTION:Delete or disable any dormant accounts after a period of 45 days of inactivity, where supported.;TITLE:Maintain an Inventory of Accounts CONTROL:v7 16.6 DESCRIPTION:Maintain an inventory of all accounts organized by authentication system.;TITLE:Disable Any Unassociated Accounts CONTROL:v7 16.8 DESCRIPTION:Disable any account that cannot be associated with a business process or business owner.; | L44: 5.1 | M44: 5.3 | O44: X | P44: X | Q44: X | R44: 16.6 | S44: 16.8 | U44: X | V44: X | W44: X | X44: https://learn.microsoft.com/en-us/entra/external-id/user-properties:https://learn.microsoft.com/en-us/entra/fundamentals/how-to-create-delete-users#delete-a-user:https://learn.microsoft.com/en-us/security/benchmark/azure/mcsb-privileged-access#pa-4-review-and-reconcile-user-access-regularly:https://www.microsoft.com/en-us/security/business/microsoft-entra-pricing:https://learn.microsoft.com/en-us/entra/identity/monitoring-health/howto-manage-inactive-user-accounts:https://learn.microsoft.com/en-us/entra/fundamentals/users-restore | Y44: By default no guest users are created.
A45: 5.3 | B45: 5.3.3 | C45: Ensure that use of the 'User Access Administrator' role is restricted | D45: Automated | E45: The User Access Administrator role grants the ability to view all resources and manage access assignments at any subscription or management group level within the tenant. Due to its high privilege level, this role assignment should be removed immediately after completing the necessary changes at the root scope to minimize security risks. | F45: The User Access Administrator role provides extensive access control privileges. Unnecessary assignments heighten the risk of privilege escalation and unauthorized access. Removing the role immediately after use minimizes security exposure. | G45: Increased administrative effort to manage and remove role assignments appropriately. | H45: **Remediate from Azure Portal** 1. From Azure Home select the Portal Menu. 1. Select `Subscriptions`. 1. Select a subscription. 1. Select `Access control (IAM)`. 1. Look for the following banner at the top of the page: `Action required: X users have elevated access in your tenant. You should take immediate action and remove all role assignments with elevated access.` 1. Click `View role assignments`. 1. Click `Remove`. **Remediate from Azure CLI** Run the following command: ``` az role assignment delete --role "User Access Administrator" --scope "/" ``` | I45: **Audit from Azure Portal** 1. From Azure Home select the Portal Menu. 1. Select `Subscriptions`. 1. Select a subscription. 1. Select `Access control (IAM)`. 1. Look for the following banner at the top of the page: `Action required: X users have elevated access in your tenant. You should take immediate action and remove all role assignments with elevated access.` If the banner is displayed, the `User Access Administrator` is assigned. **Audit from Azure CLI** Run the following command: ``` az role assignment list --role "User Access Administrator" --scope "/" ``` Ensure that the command does not return any `User Access Administrator` role assignment information. | K45: TITLE:Define and Maintain Role-Based Access Control CONTROL:v8 6.8 DESCRIPTION:Define and maintain role-based access control, through determining and documenting the access rights necessary for each role within the enterprise to successfully carry out its assigned duties. Perform access control reviews of enterprise assets to validate that all privileges are authorized, on a recurring schedule at a minimum annually, or more frequently.;TITLE:Maintain Inventory of Administrative Accounts CONTROL:v7 4.1 DESCRIPTION:Use automated tools to inventory all administrative accounts, including domain and local accounts, to ensure that only authorized individuals have elevated privileges.; | L45: 6.8 | Q45: X | R45: 4.1 | V45: X | W45: X | X45: https://learn.microsoft.com/en-us/azure/role-based-access-control/built-in-roles:https://learn.microsoft.com/en-us/azure/role-based-access-control/elevate-access-global-admin
A46: 5.3 | B46: 5.3.4 | C46: Ensure that all 'privileged' role assignments are periodically reviewed | D46: Manual | E46: Periodic review of privileged role assignments is performed to ensure that the privileged roles assigned to users are accurate and appropriate. | F46: Privileged roles are crown jewel assets that can be used by malicious insiders, threat actors, and even through mistake to significantly damage an organization in numerous ways. These roles should be periodically reviewed to: - identify lingering permissions assignment (e.g. an administrator has been terminated, the administrator account is being retained, but the permissions are no longer necessary and has not been properly addressed by process) - detect lateral movement through privilege escalation (e.g. an account with administrative permission has been compromised and is elevating other accounts in an attempt to circumvent detection mechanisms) | G46: Increased administrative effort to manage and remove role assignments appropriately. | I46: **Audit from Azure Portal** 1. From Azure Home select the Portal Menu. 1. Select `Subscriptions`. 1. Select a subscription. 1. Select `Access control (IAM)`. 1. Look for the number under the word `Privileged` accompanied by a link titled `View Assignments.` Click the `View assignments` link. 1. For each privileged role listed, evaluate whether the assignment is appropriate and current for each User, Group, or App assigned to each privileged role. **NOTE:** The judgement of what constitutes 'appropriate and current' assignments requires a clear understanding of your organization's personnel, systems, policy, and security requirements. This cannot be effectively prescribed in procedure. | K46: TITLE:Define and Maintain Role-Based Access Control CONTROL:v8 6.8 DESCRIPTION:Define and maintain role-based access control, through determining and documenting the access rights necessary for each role within the enterprise to successfully carry out its assigned duties. Perform access control reviews of enterprise assets to validate that all privileges are authorized, on a recurring schedule at a minimum annually, or more frequently.;TITLE:Maintain Inventory of Administrative Accounts CONTROL:v7 4.1 DESCRIPTION:Use automated tools to inventory all administrative accounts, including domain and local accounts, to ensure that only authorized individuals have elevated privileges.; | L46: 6.8 | Q46: X | R46: 4.1 | V46: X | W46: X | X46: https://learn.microsoft.com/en-us/azure/role-based-access-control/built-in-roles
A47: 5.3 | B47: 5.3.5 | C47: Ensure disabled user accounts do not have read, write, or owner permissions | D47: Manual | E47: Ensure that any roles granting read, write, or owner permissions are removed from disabled Azure user accounts. While an automated assessment procedure exists for this recommendation, the assessment status remains manual. Removing role assignments from disabled user accounts depends on the context and requirements of each organization and environment. | F47: Disabled accounts should not retain access to resources, as this poses a security risk. Removing role assignments mitigates potential unauthorized access and enforces the principle of least privilege. | G47: Ensure disabled accounts are not relied on for break glass or automated processes before removing roles to avoid service disruption. | H47: **Remediate from Azure Portal** 1. Go to `Microsoft Entra ID`. 1. Under `Manage`, click `Users`. 1. Click `Add filter`. 1. Click `Account enabled`. 1. Click the toggle switch to set the value to `No`. 1. Click `Apply`. 1. Click the `Display name` of a disabled user account with read, write, or owner roles assigned. 1. Click `Azure role assignments`. 1. Click the name of a read, write, or owner role. 1. Click `Assignments`. 1. Click `Remove` in the row for the disabled user account. 1. Click `Yes`. 1. Repeat steps 7-12 for disabled user accounts requiring remediation. **Remediate from PowerShell** For each account requiring remediation, run the following command to remove an assigned role: ``` Remove-AzRoleAssignment -ObjectId $user.ObjectId -RoleDefinitionName <role-definition-name> ``` | I47: **Audit from Azure Portal** 1. Go to `Microsoft Entra ID`. 1. Under `Manage`, click `Users`. 1. Click `Add filter`. 1. Click `Account enabled`. 1. Click the toggle switch to set the value to `No`. 1. Click `Apply`. 1. Click the `Display name` of a disabled user account. 1. Click `Azure role assignments`. 1. Ensure that no read, write, or owner roles are assigned to the user account. 1. Repeat steps 7-9 for each disabled user account. **Audit from PowerShell** Run the following command to connect to Microsoft Entra ID: ``` Connect-AzureAD ``` Run the following command to list users: ``` Get-AzureADUser ``` Run the following command to get a user: ``` $user = Get-AzureADUser -ObjectId <object-id> ``` Run the following command to get the `AccountEnabled` setting for the user: ``` $user.AccountEnabled ``` If `AccountEnabled` is `False`, run the following command to get the role assignments for the user: ``` Get-AzRoleAssignment -ObjectId $user.ObjectId ``` Ensure that no read, write, or owner roles are assigned to the user. Repeat for each user. **Audit from Azure Policy** If referencing a digital copy of this Benchmark, clicking a Policy ID will open a link to the associated Policy definition in Azure. If referencing a printed copy, you can search Policy IDs from this URL: https://portal.azure.com/#view/Microsoft_Azure_Policy/PolicyMenuBlade/~/Definitions - **Policy ID:** [0cfea604-3201-4e14-88fc-fae4c427a6c5](https://portal.azure.com/#view/Microsoft_Azure_Policy/PolicyDetailBlade/definitionId/%2Fproviders%2FMicrosoft.Authorization%2FpolicyDefinitions%2F0cfea604-3201-4e14-88fc-fae4c427a6c5) **- Name:** 'Blocked accounts with owner permissions on Azure resources should be removed' - **Policy ID:** [8d7e1fde-fe26-4b5f-8108-f8e432cbc2be](https://portal.azure.com/#view/Microsoft_Azure_Policy/PolicyDetailBlade/definitionId/%2Fproviders%2FMicrosoft.Authorization%2FpolicyDefinitions%2F8d7e1fde-fe26-4b5f-8108-f8e432cbc2be) **- Name:** 'Blocked accounts with read and write permissions on Azure resources should be removed' | K47: TITLE:Establish and Maintain an Inventory of Accounts CONTROL:v8 5.1 DESCRIPTION:Establish and maintain an inventory of all accounts managed in the enterprise. The inventory must include both user and administrator accounts. The inventory, at a minimum, should contain the person’s name, username, start/stop dates, and department. Validate that all active accounts are authorized, on a recurring schedule at a minimum quarterly, or more frequently.;TITLE:Maintain an Inventory of Accounts CONTROL:v7 16.6 DESCRIPTION:Maintain an inventory of all accounts organized by authentication system.; | L47: 5.1 | O47: X | P47: X | Q47: X | R47: 16.6 | V47: X | W47: X | X47: https://learn.microsoft.com/en-us/powershell/module/az.resources/get-azaduser:https://learn.microsoft.com/en-us/powershell/module/az.resources/get-azroleassignment:https://learn.microsoft.com/en-us/powershell/module/az.resources/remove-azroleassignment | Y47: Disabled user accounts retain their prior role assignments.
A48: 5.3 | B48: 5.3.6 | C48: Ensure 'Tenant Creator' role assignments are periodically reviewed | D48: Manual | E48: Perform a periodic review of the Tenant Creator role assignment to ensure that the assignments are accurate and appropriate. This recommendation should be applied alongside the recommendation **"Ensure that 'Restrict non-admin users from creating tenants' is set to 'Yes'"**. | F48: Unnecessary assignments increase the risk of privilege escalation and unauthorized access. | G48: Verify that the Tenant Creator role is no longer required by any assignments before removal to avoid disruption of critical functions. | H48: **Remediate from Azure Portal** 1. Go to `Microsoft Entra ID`. 1. Under `Manage`, click `Roles and administrators`. 1. In the search bar, type `Tenant Creator`. 1. Click the role. 1. Click the name of an assignment. 1. Check the box next to the `Tenant Creator` role. 1. Click `X Remove assignments`. 1. Click `Yes`. 1. Repeat steps 1-8 for each assignment requiring remediation. | I48: **Audit from Azure Portal** 1. Go to `Microsoft Entra ID`. 1. Under `Manage`, click `Roles and administrators`. 1. In the search bar, type `Tenant Creator`. 1. Click the role. 1. Review the assignments and ensure that they are appropriate. | K48: TITLE:Restrict Administrator Privileges to Dedicated Administrator Accounts CONTROL:v8 5.4 DESCRIPTION:Restrict administrator privileges to dedicated administrator accounts on enterprise assets. Conduct general computing activities, such as internet browsing, email, and productivity suite use, from the user’s primary, non-privileged account.;TITLE:Ensure the Use of Dedicated Administrative Accounts CONTROL:v7 4.3 DESCRIPTION:Ensure that all users with administrative account access use a dedicated or secondary account for elevated activities. This account should only be used for administrative activities and not internet browsing, email, or similar activities.; | L48: 5.4 | O48: X | P48: X | Q48: X | R48: 4.3 | U48: X | V48: X | W48: X | X48: https://learn.microsoft.com/en-us/azure/active-directory-b2c/tenant-management-check-tenant-creation-permission:https://learn.microsoft.com/en-us/entra/identity/role-based-access-control/permissions-reference#tenant-creator | Y48: The Tenant Creator role is not assigned by default.
A49: 5.3 | B49: 5.3.7 | C49: Ensure all non-privileged role assignments are periodically reviewed | D49: Manual | E49: Perform a periodic review of non-privileged role assignments to ensure that the non-privileged roles assigned to users are appropriate. **Note:** Determining 'appropriate' assignments requires a clear understanding of your organization's personnel, systems, policies, and security requirements. This cannot be effectively prescribed in a procedure. | F49: To ensure the principle of least privilege is followed, non-privileged role assignments should be reviewed periodically to confirm that users are granted only the minimum level of permissions they need to perform their tasks. | G49: Increased administrative effort to manage and remove role assignments appropriately. | H49: **Remediate from Azure Portal** 1. Go to `Subscriptions`. 1. Click the name of a subscription. 1. Click `Access control (IAM)`. 1. Click `Role assignments`. 1. Click `Job function roles`. 1. Check the box next to any inappropriate assignments. 1. Click `Delete`. 1. Click `Yes`. 1. Repeat steps 1-8 for each subscription. | I49: **Audit from Azure Portal** 1. Go to `Subscriptions`. 1. Click the name of a subscription. 1. Click `Access control (IAM)`. 1. Click `Role assignments`. 1. Click `Job function roles`. 1. For each role, ensure the assignments are appropriate. 1. Repeat steps 1-6 for each subscription. | K49: TITLE:Define and Maintain Role-Based Access Control CONTROL:v8 6.8 DESCRIPTION:Define and maintain role-based access control, through determining and documenting the access rights necessary for each role within the enterprise to successfully carry out its assigned duties. Perform access control reviews of enterprise assets to validate that all privileges are authorized, on a recurring schedule at a minimum annually, or more frequently.;TITLE:Maintain an Inventory of Accounts CONTROL:v7 16.6 DESCRIPTION:Maintain an inventory of all accounts organized by authentication system.; | L49: 6.8 | Q49: X | R49: 16.6 | V49: X | W49: X | X49: https://learn.microsoft.com/en-us/azure/role-based-access-control/role-assignments | Y49: Users do not have non-privileged roles assigned to them by default.
A50: 6 | C50: Management and Governance Services | E50: To better understand the relationship between the Foundations Benchmark and Services Benchmarks, please read the "Introduction" section of this document. Azure Product Directory Reference: https://azure.microsoft.com/en-us/products#management-and-governance **FEEDBACK REQUEST:** Is there a specific service or recommendation in this section that you'd like to see addressed or improved? Let us know by making a ticket or starting a discussion in the CIS Microsoft Azure Community (https://workbench.cisecurity.org/communities/72).
A51: 6.1 | C51: Logging and Monitoring | E51: This section covers security recommendations to follow for logging and monitoring policies on an Azure Subscription. **Scoping: A necessary exercise for effective and efficient use of Logging and Monitoring** For recommendations contained in this section, it is crucial that your organization consider and settle on the scope of application for each recommendation individually. The scope of application cannot be realistically written in a generic prescriptive way within these recommendations, so a scoping exercise is strongly recommended. A scoping exercise will help you determine which resources are "in scope" and will receive partial or complete logging and monitoring treatment, and which resources are "out of scope" and will not receive any logging and monitoring treatment. Your objectives with the scoping exercise should be to: - Produce a clear classification of resources - Understand the control requirements of any relevant security or compliance frameworks - Ensure the appropriate personnel can detect and react to threats - Ensure relevant resources have a historical register for accountability and investigation - Minimize alert fatigue and cost Release Environments provide a helpful context for understanding scope from a DevOps perspective. For example: 1. Production Environment 1. Staging Environment 1. Testing Environment 1. Development Environment While resources considered in the scope of a Production Environment might have a full set of recommendations applied for logging and monitoring, other release environments might have a limited set of recommendations applied for the sake of accountability. The names of these environments and which resources are in the scope of each environment will vary from one organization to another.
A52: 6.1 | B52: 6.1.4 | C52: Ensure that Azure Monitor Resource Logging is Enabled for All Services that Support it | D52: Manual | E52: Resource Logs capture activity to the data access plane while the Activity log is a subscription-level log for the control plane. Resource-level diagnostic logs provide insight into operations that were performed within that resource itself; for example, reading or updating a secret from a Key Vault. Currently, 95 Azure resources support Azure Monitoring (See the more information section for a complete list), including Network Security Groups, Load Balancers, Key Vault, AD, Logic Apps, and CosmosDB. The content of these logs varies by resource type. A number of back-end services were not configured to log and store Resource Logs for certain activities or for a sufficient length. It is crucial that monitoring is correctly configured to log all relevant activities and retain those logs for a sufficient length of time. Given that the mean time to detection in an enterprise is 240 days, a minimum retention period of two years is recommended. While an automated assessment procedure exists for this recommendation, the assessment status remains manual. Determining whether resource logging should be enabled for specific resources depends on the context and requirements of each organization and environment. | F52: A lack of monitoring reduces the visibility into the data plane, and therefore an organization's ability to detect reconnaissance, authorization attempts or other malicious activity. Unlike Activity Logs, Resource Logs are not enabled by default. Specifically, without monitoring it would be impossible to tell which entities had accessed a data store that was breached. In addition, alerts for failed attempts to access APIs for Web Services or Databases are only possible when logging is enabled. This recommendation's Level 1 profile is dependent upon the free level of retention of 30 days. More than 30 days retention of resource logs will increase the cost of this recommendation. | G52: Costs for monitoring varies with Log Volume. Not every resource needs to have logging enabled. It is important to determine the security classification of the data being processed by the given resource and adjust the logging based on which events need to be tracked. This is typically determined by governance and compliance requirements. | H52: Azure Subscriptions should log every access and operation for all resources. Logs should be sent to Storage and a Log Analytics Workspace or equivalent third-party system. Logs should be kept in readily-accessible storage for a minimum of one year, and then moved to inexpensive cold storage for a duration of time as necessary. If retention policies are set but storing logs in a Storage Account is disabled (for example, if only Event Hubs or Log Analytics options are selected), the retention policies have no effect. Enable all monitoring at first, and then be more aggressive moving data to cold storage if the volume of data becomes a cost concern. **Remediate from Azure Portal** The specific steps for configuring resources within the Azure console vary depending on resource, but typically the steps are: 1. Go to the resource 2. Click on Diagnostic settings 3. In the blade that appears, click "Add diagnostic setting" 4. Configure the diagnostic settings 5. Click on Save **Remediate from Azure CLI** For each `resource`, run the following making sure to use a `resource` appropriate JSON encoded `category` for the `--logs` option. ``` az monitor diagnostic-settings create --name <diagnostic settings name> --resource <resource ID> --logs "[{category:<resource specific category>,enabled:true,rentention-policy:{enabled:true,days:180}}]" --metrics "[{category:AllMetrics,enabled:true,retention-policy:{enabled:true,days:180}}]" <[--event-hub <event hub ID> --event-hub-rule <event hub auth rule ID> | --storage-account <storage account ID> |--workspace <log analytics workspace ID> | --marketplace-partner-id <full resource ID of third-party solution>]> ``` **Remediate from PowerShell** Create the `log` settings object ``` $logSettings = @() $logSettings += New-AzDiagnosticSettingLogSettingsObject -Enabled $true -RetentionPolicyDay 180 -RetentionPolicyEnabled $true -Category <resource specific category> $logSettings += New-AzDiagnosticSettingLogSettingsObject -Enabled $true -RetentionPolicyDay 180 -RetentionPolicyEnabled $true -Category <resource specific category number 2> ``` Create the `metric` settings object ``` $metricSettings = @() $metricSettings += New-AzDiagnosticSettingMetricSettingsObject -Enabled $true -RetentionPolicyDay 180 -RetentionPolicyEnabled $true -Category AllMetrics ``` Create the diagnostic setting for a specific resource ``` New-AzDiagnosticSetting -Name "<diagnostic settings name>" -ResourceId <resource ID> -Log $logSettings -Metric $metricSettings ``` | I52: **Audit from Azure Portal** The specific steps for configuring resources within the Azure console vary depending on resource, but typically the steps are: 1. Go to the resource 2. Click on Diagnostic settings 3. In the blade that appears, click "Add diagnostic setting" 4. Configure the diagnostic settings 5. Click on Save **Audit from Azure CLI** List all `resources` for a `subscription` ``` az resource list --subscription <subscription id> ``` For each `resource` run the following ``` az monitor diagnostic-settings list --resource <resource ID> ``` An empty result means a `diagnostic settings` is not configured for that resource. An error message means a `diagnostic settings` is not supported for that resource. **Audit from PowerShell** Get a list of `resources` in a `subscription` context and store in a variable ``` $resources = Get-AzResource ``` Loop through each `resource` to determine if a diagnostic setting is configured or not. ``` foreach ($resource in $resources) {$diagnosticSetting = Get-AzDiagnosticSetting -ResourceId $resource.id -ErrorAction "SilentlyContinue"; if ([string]::IsNullOrEmpty($diagnosticSetting)) {$message = "Diagnostic Settings not configured for resource: " + $resource.Name;Write-Output $message}else{$diagnosticSetting}} ``` A result of `Diagnostic Settings not configured for resource: <resource name>` means a `diagnostic settings` is not configured for that resource. Otherwise, the output of the above command will show configured `Diagnostic Settings` for a resource. **Audit from Azure Policy** If referencing a digital copy of this Benchmark, clicking a Policy ID will open a link to the associated Policy definition in Azure. If referencing a printed copy, you can search Policy IDs from this URL: https://portal.azure.com/#view/Microsoft_Azure_Policy/PolicyMenuBlade/~/Definitions - **Policy ID:** [cf820ca0-f99e-4f3e-84fb-66e913812d21](https://portal.azure.com/#view/Microsoft_Azure_Policy/PolicyDetailBlade/definitionId/%2Fproviders%2FMicrosoft.Authorization%2FpolicyDefinitions%2Fcf820ca0-f99e-4f3e-84fb-66e913812d21) **- Name:** 'Resource logs in Key Vault should be enabled' - **Policy ID:** [91a78b24-f231-4a8a-8da9-02c35b2b6510](https://portal.azure.com/#view/Microsoft_Azure_Policy/PolicyDetailBlade/definitionId/%2Fproviders%2FMicrosoft.Authorization%2FpolicyDefinitions%2F91a78b24-f231-4a8a-8da9-02c35b2b6510) **- Name:** 'App Service apps should have resource logs enabled' - **Policy ID:** [428256e6-1fac-4f48-a757-df34c2b3336d](https://portal.azure.com/#view/Microsoft_Azure_Policy/PolicyDetailBlade/definitionId/%2Fproviders%2FMicrosoft.Authorization%2FpolicyDefinitions%2F428256e6-1fac-4f48-a757-df34c2b3336d) **- Name:** 'Resource logs in Batch accounts should be enabled' - **Policy ID:** [057ef27e-665e-4328-8ea3-04b3122bd9fb](https://portal.azure.com/#view/Microsoft_Azure_Policy/PolicyDetailBlade/definitionId/%2Fproviders%2FMicrosoft.Authorization%2FpolicyDefinitions%2F057ef27e-665e-4328-8ea3-04b3122bd9fb) **- Name:** 'Resource logs in Azure Data Lake Store should be enabled' - **Policy ID:** [c95c74d9-38fe-4f0d-af86-0c7d626a315c](https://portal.azure.com/#view/Microsoft_Azure_Policy/PolicyDetailBlade/definitionId/%2Fproviders%2FMicrosoft.Authorization%2FpolicyDefinitions%2Fc95c74d9-38fe-4f0d-af86-0c7d626a315c) **- Name:** 'Resource logs in Data Lake Analytics should be enabled' - **Policy ID:** [83a214f7-d01a-484b-91a9-ed54470c9a6a](https://portal.azure.com/#view/Microsoft_Azure_Policy/PolicyDetailBlade/definitionId/%2Fproviders%2FMicrosoft.Authorization%2FpolicyDefinitions%2F83a214f7-d01a-484b-91a9-ed54470c9a6a) **- Name:** 'Resource logs in Event Hub should be enabled' - **Policy ID:** [383856f8-de7f-44a2-81fc-e5135b5c2aa4](https://portal.azure.com/#view/Microsoft_Azure_Policy/PolicyDetailBlade/definitionId/%2Fproviders%2FMicrosoft.Authorization%2FpolicyDefinitions%2F383856f8-de7f-44a2-81fc-e5135b5c2aa4) **- Name:** 'Resource logs in IoT Hub should be enabled' - **Policy ID:** [34f95f76-5386-4de7-b824-0d8478470c9d](https://portal.azure.com/#view/Microsoft_Azure_Policy/PolicyDetailBlade/definitionId/%2Fproviders%2FMicrosoft.Authorization%2FpolicyDefinitions%2F34f95f76-5386-4de7-b824-0d8478470c9d) **- Name:** 'Resource logs in Logic Apps should be enabled' - **Policy ID:** [b4330a05-a843-4bc8-bf9a-cacce50c67f4](https://portal.azure.com/#view/Microsoft_Azure_Policy/PolicyDetailBlade/definitionId/%2Fproviders%2FMicrosoft.Authorization%2FpolicyDefinitions%2Fb4330a05-a843-4bc8-bf9a-cacce50c67f4) **- Name:** 'Resource logs in Search services should be enabled' - **Policy ID:** [f8d36e2f-389b-4ee4-898d-21aeb69a0f45](https://portal.azure.com/#view/Microsoft_Azure_Policy/PolicyDetailBlade/definitionId/%2Fproviders%2FMicrosoft.Authorization%2FpolicyDefinitions%2Ff8d36e2f-389b-4ee4-898d-21aeb69a0f45) **- Name:** 'Resource logs in Service Bus should be enabled' - **Policy ID:** [f9be5368-9bf5-4b84-9e0a-7850da98bb46](https://portal.azure.com/#view/Microsoft_Azure_Policy/PolicyDetailBlade/definitionId/%2Fproviders%2FMicrosoft.Authorization%2FpolicyDefinitions%2Ff9be5368-9bf5-4b84-9e0a-7850da98bb46) **- Name:** 'Resource logs in Azure Stream Analytics should be enabled' - **Policy ID:** [8a04f872-51e9-4313-97fb-fc1c3543011c](https://portal.azure.com/#view/Microsoft_Azure_Policy/PolicyDetailBlade/definitionId/%2Fproviders%2FMicrosoft.Authorization%2FpolicyDefinitions%2F8a04f872-51e9-4313-97fb-fc1c3543011c) **- Name:** 'Azure Application Gateway should have Resource logs enabled' | J52: For an up-to-date list of Azure resources which support Azure Monitor, refer to the "Supported Log Categories" reference. | K52: TITLE:Collect Detailed Audit Logs CONTROL:v8 8.5 DESCRIPTION:Configure detailed audit logging for enterprise assets containing sensitive data. Include event source, date, username, timestamp, source addresses, destination addresses, and other useful elements that could assist in a forensic investigation.;TITLE:Centralize Audit Logs CONTROL:v8 8.9 DESCRIPTION:Centralize, to the extent possible, audit log collection and retention across enterprise assets.;TITLE:Enable Detailed Logging CONTROL:v7 6.3 DESCRIPTION:Enable system logging to include detailed information such as an event source, date, user, timestamp, source addresses, destination addresses, and other useful elements.;TITLE:Central Log Management CONTROL:v7 6.5 DESCRIPTION:Ensure that appropriate logs are being aggregated to a central log management system for analysis and review.; | L52: 8.5 | M52: 8.9 | P52: X | Q52: X | R52: 6.3 | S52: 6.5 | V52: X | W52: X | X52: https://learn.microsoft.com/en-us/security/benchmark/azure/mcsb-logging-threat-detection#lt-3-enable-logging-for-security-investigation:https://learn.microsoft.com/en-us/security/benchmark/azure/mcsb-logging-threat-detection#lt-5-centralize-security-log-management-and-analysis:https://learn.microsoft.com/en-us/azure/azure-monitor/essentials/monitor-azure-resource:Supported Log Categories: https://learn.microsoft.com/en-us/azure/azure-monitor/reference/logs-index:Logs and Audit - Fundamentals: https://learn.microsoft.com/en-us/azure/security/fundamentals/log-audit:Collecting Logs: https://learn.microsoft.com/en-us/azure/azure-monitor/essentials/activity-log:Key Vault Logging: https://learn.microsoft.com/en-us/azure/key-vault/general/logging:Monitor Diagnostic Settings: https://learn.microsoft.com/en-us/cli/azure/monitor/diagnostic-settings:Overview of Diagnostic Logs: https://learn.microsoft.com/en-us/azure/azure-monitor/fundamentals/data-sources:Supported Services for Diagnostic Logs: https://learn.microsoft.com/en-us/azure/azure-monitor/essentials/resource-logs-schema:Diagnostic Logs for CDNs: https://learn.microsoft.com/en-us/azure/cdn/cdn-azure-diagnostic-logs | Y52: By default, Azure Monitor Resource Logs are 'Disabled' for all resources.
A53: 6.1.1 | C53: Configuring Diagnostic Settings | E53: The Azure Diagnostic Settings capture control/management activities performed on a subscription or Azure AD Tenant. By default, the Azure Portal retains activity logs only for 90 days. The Diagnostic Settings define the type of events that are stored or streamed and the outputs—storage account, log analytics workspace, event hub, and others. The Diagnostic Settings, if configured properly, can ensure that all logs are retained for longer duration. This section has recommendations for correctly configuring the Diagnostic Settings so that all logs captured are retained for longer periods. **Azure Subscriptions** When configuring Diagnostic Settings, you may choose to export in one of four ways in which you need to ensure appropriate data retention. The options are Log Analytics workspace, Event Hub, Storage Account, and Partner Solutions. It is important to ensure you are aware and have set retention as your organization sees fit. **Azure AD Logs** In order to retain sign in logs, user account changes, application provisioning logs, or other logs that are visible to only on the Tenant in Azure AD, separate Diagnostic settings must be specified. **Deployment by Policy** Deploying Azure diagnostics should ideally be done by policy to ensure a consistent configuration. Microsoft provides a full set of policies for all diagnostic capable resource types in their GitHub repository. If you chose to deploy by policy, it is best to route the diagnostics to a Log Analytics Workspace so that they can be used in Azure Monitor or Azure Sentinel. Be aware that this has a cost attached to it. Future versions of the CIS Azure Foundations Benchmark will aim to cover the use of policy in greater detail.
A54: 6.1.1 | B54: 6.1.1.1 | C54: Ensure that a 'Diagnostic Setting' exists for Subscription Activity Logs | D54: Automated | E54: Enable Diagnostic settings for exporting activity logs. Diagnostic settings are available for each individual resource within a subscription. Settings should be configured for all appropriate resources for your environment. | F54: A diagnostic setting controls how a diagnostic log is exported. By default, logs are retained only for 90 days. Diagnostic settings should be defined so that logs can be exported and stored for a longer duration to analyze security activities within an Azure subscription. | H54: **Remediate from Azure Portal** To enable Diagnostic Settings on a Subscription: 1. Go to `Monitor` 2. Click on `Activity log` 3. Click on `Export Activity Logs` 4. Click `+ Add diagnostic setting` 5. Enter a `Diagnostic setting name` 6. Select `Categories` for the diagnostic setting 7. Select the appropriate `Destination details` (this may be Log Analytics, Storage Account, Event Hub, or Partner solution) 8. Click `Save` To enable Diagnostic Settings on a specific resource: 1. Go to `Monitoring` 1. Click `Diagnostic settings` 1. Select `Add diagnostic setting` 1. Enter a `Diagnostic setting name` 1. Select the appropriate log, metric, and destination (this may be Log Analytics, Storage Account, Event Hub, or Partner solution) 1. Click `Save` Repeat these step for all resources as needed. **Remediate from Azure CLI** To configure Diagnostic Settings on a Subscription: ``` az monitor diagnostic-settings subscription create --subscription <subscription id> --name <diagnostic settings name> --location <location> <[--event-hub <event hub ID> --event-hub-auth-rule <event hub auth rule ID>] [--storage-account <storage account ID>] [--workspace <log analytics workspace ID>] --logs "<JSON encoded categories>" (e.g. [{category:Security,enabled:true},{category:Administrative,enabled:true},{category:Alert,enabled:true},{category:Policy,enabled:true}]) ``` To configure Diagnostic Settings on a specific resource: ``` az monitor diagnostic-settings create --subscription <subscription ID> --resource <resource ID> --name <diagnostic settings name> <[--event-hub <event hub ID> --event-hub-rule <event hub auth rule ID>] [--storage-account <storage account ID>] [--workspace <log analytics workspace ID>] --logs <resource specific JSON encoded log settings> --metrics <metric settings (shorthand|json-file|yaml-file)> ``` **Remediate from PowerShell** To configure Diagnostic Settings on a subscription: ``` $logCategories = @(); $logCategories += New-AzDiagnosticSettingSubscriptionLogSettingsObject -Category Administrative -Enabled $true $logCategories += New-AzDiagnosticSettingSubscriptionLogSettingsObject -Category Security -Enabled $true $logCategories += New-AzDiagnosticSettingSubscriptionLogSettingsObject -Category ServiceHealth -Enabled $true $logCategories += New-AzDiagnosticSettingSubscriptionLogSettingsObject -Category Alert -Enabled $true $logCategories += New-AzDiagnosticSettingSubscriptionLogSettingsObject -Category Recommendation -Enabled $true $logCategories += New-AzDiagnosticSettingSubscriptionLogSettingsObject -Category Policy -Enabled $true $logCategories += New-AzDiagnosticSettingSubscriptionLogSettingsObject -Category Autoscale -Enabled $true $logCategories += New-AzDiagnosticSettingSubscriptionLogSettingsObject -Category ResourceHealth -Enabled $true New-AzSubscriptionDiagnosticSetting -SubscriptionId <subscription ID> -Name <Diagnostic settings name> <[-EventHubAuthorizationRule <event hub auth rule ID> -EventHubName <event hub name>] [-StorageAccountId <storage account ID>] [-WorkSpaceId <log analytics workspace ID>] [-MarketplacePartner ID <full ARM Marketplace resource ID>]> -Log $logCategories ``` To configure Diagnostic Settings on a specific resource: ``` $logCategories = @() $logCategories += New-AzDiagnosticSettingLogSettingsObject -Category <resource specific log category> -Enabled $true Repeat command and variable assignment for each Log category specific to the resource where this Diagnostic Setting will get configured. $metricCategories = @() $metricCategories += New-AzDiagnosticSettingMetricSettingsObject -Enabled $true [-Category <resource specific metric category | AllMetrics>] [-RetentionPolicyDay <Integer>] [-RetentionPolicyEnabled $true] Repeat command and variable assignment for each Metric category or use the 'AllMetrics' category. New-AzDiagnosticSetting -ResourceId <resource ID> -Name <Diagnostic settings name> -Log $logCategories -Metric $metricCategories [-EventHubAuthorizationRuleId <event hub auth rule ID> -EventHubName <event hub name>] [-StorageAccountId <storage account ID>] [-WorkspaceId <log analytics workspace ID>] [-MarketplacePartnerId <full ARM marketplace resource ID>]> | I54: **Audit from Azure Portal** To identify Diagnostic Settings on a subscription: 1. Go to `Monitor` 2. Click `Activity Log` 3. Click `Export Activity Logs` 4. Select a `Subscription` 5. Ensure a `Diagnostic setting` exists for the selected Subscription To identify Diagnostic Settings on specific resources: 1. Go to `Monitoring` 2. Click `Diagnostic settings` 3. Ensure a `Diagnostic setting` exists for all appropriate resources. **Audit from Azure CLI** To identify Diagnostic Settings on a subscription: ``` az monitor diagnostic-settings subscription list --subscription <subscription-id> ``` To identify Diagnostic Settings on a resource ``` az monitor diagnostic-settings list --resource <resource-id> ``` **Audit from PowerShell** To identify Diagnostic Settings on a Subscription: ``` Get-AzSubscriptionDiagnosticSetting -SubscriptionId <subscription-id> ``` To identify Diagnostic Settings on a specific resource: ``` Get-AzDiagnosticSetting -ResourceId <resource-id> ``` | K54: TITLE:Centralize Audit Logs CONTROL:v8 8.9 DESCRIPTION:Centralize, to the extent possible, audit log collection and retention across enterprise assets.;TITLE:Central Log Management CONTROL:v7 6.5 DESCRIPTION:Ensure that appropriate logs are being aggregated to a central log management system for analysis and review.; | L54: 8.9 | P54: X | Q54: X | R54: 6.5 | V54: X | W54: X | X54: https://learn.microsoft.com/en-us/azure/azure-monitor/fundamentals/data-sources:https://learn.microsoft.com/en-us/cli/azure/monitor/diagnostic-settings?view=azure-cli-latest:https://learn.microsoft.com/en-us/security/benchmark/azure/mcsb-logging-threat-detection#lt-3-enable-logging-for-security-investigation | Y54: By default, diagnostic setting is not set.
A55: 6.1.1 | B55: 6.1.1.2 | C55: Ensure Diagnostic Setting captures appropriate categories | D55: Automated | E55: **Prerequisite**: A Diagnostic Setting must exist. If a Diagnostic Setting does not exist, the navigation and options within this recommendation will not be available. Please review the recommendation at the beginning of this subsection titled: "Ensure that a 'Diagnostic Setting' exists." The diagnostic setting should be configured to log the appropriate activities from the control/management plane. | F55: A diagnostic setting controls how the diagnostic log is exported. Capturing the diagnostic setting categories for appropriate control/management plane activities allows proper alerting. | H55: **Remediate from Azure Portal** 1. Go to `Monitor`. 1. Click `Activity log`. 1. Click on `Export Activity Logs`. 1. Select the `Subscription` from the drop down menu. 1. Click `Edit setting` next to a diagnostic setting. 1. Check the following categories: `Administrative, Alert, Policy, and Security`. 1. Choose the destination details according to your organization's needs. 1. Click `Save`. **Remediate from Azure CLI** ``` az monitor diagnostic-settings subscription create --subscription <subscription id> --name <diagnostic settings name> --location <location> <[--event-hub <event hub ID> --event-hub-auth-rule <event hub auth rule ID>] [--storage-account <storage account ID>] [--workspace <log analytics workspace ID>] --logs "[{category:Security,enabled:true},{category:Administrative,enabled:true},{category:Alert,enabled:true},{category:Policy,enabled:true}]" ``` **Remediate from PowerShell** ``` $logCategories = @(); $logCategories += New-AzDiagnosticSettingSubscriptionLogSettingsObject -Category Administrative -Enabled $true $logCategories += New-AzDiagnosticSettingSubscriptionLogSettingsObject -Category Security -Enabled $true $logCategories += New-AzDiagnosticSettingSubscriptionLogSettingsObject -Category Alert -Enabled $true $logCategories += New-AzDiagnosticSettingSubscriptionLogSettingsObject -Category Policy -Enabled $true New-AzSubscriptionDiagnosticSetting -SubscriptionId <subscription ID> -Name <Diagnostic settings name> <[-EventHubAuthorizationRule <event hub auth rule ID> -EventHubName <event hub name>] [-StorageAccountId <storage account ID>] [-WorkSpaceId <log analytics workspace ID>] [-MarketplacePartner ID <full ARM Marketplace resource ID>]> -Log $logCategories ``` | I55: **Audit from Azure Portal** 1. Go to `Monitor`. 1. Click `Activity log`. 1. Click on `Export Activity Logs`. 1. Select the appropriate `Subscription`. 1. Click `Edit setting` next to a diagnostic setting. 1. Ensure that the following categories are checked: `Administrative, Alert, Policy, and Security`. **Audit from Azure CLI** Ensure the categories `'Administrative', 'Alert', 'Policy', and 'Security'` set to: 'enabled: true' ``` az monitor diagnostic-settings subscription list --subscription <subscription ID> ``` **Audit from PowerShell** Ensure the categories Administrative, Alert, Policy, and Security are set to Enabled:True ``` Get-AzSubscriptionDiagnosticSetting -Subscription <subscriptionID> ``` **Audit from Azure Policy** If referencing a digital copy of this Benchmark, clicking a Policy ID will open a link to the associated Policy definition in Azure. If referencing a printed copy, you can search Policy IDs from this URL: https://portal.azure.com/#view/Microsoft_Azure_Policy/PolicyMenuBlade/~/Definitions - **Policy ID:** [3b980d31-7904-4bb7-8575-5665739a8052](https://portal.azure.com/#view/Microsoft_Azure_Policy/PolicyDetailBlade/definitionId/%2Fproviders%2FMicrosoft.Authorization%2FpolicyDefinitions%2F3b980d31-7904-4bb7-8575-5665739a8052) **- Name:** 'An activity log alert should exist for specific Security operations' - **Policy ID:** [b954148f-4c11-4c38-8221-be76711e194a](https://portal.azure.com/#view/Microsoft_Azure_Policy/PolicyDetailBlade/definitionId/%2Fproviders%2FMicrosoft.Authorization%2FpolicyDefinitions%2Fb954148f-4c11-4c38-8221-be76711e194a) **- Name:** 'An activity log alert should exist for specific Administrative operations' - **Policy ID:** [c5447c04-a4d7-4ba8-a263-c9ee321a6858](https://portal.azure.com/#view/Microsoft_Azure_Policy/PolicyDetailBlade/definitionId/%2Fproviders%2FMicrosoft.Authorization%2FpolicyDefinitions%2Fc5447c04-a4d7-4ba8-a263-c9ee321a6858) **- Name:** 'An activity log alert should exist for specific Policy operations' | K55: TITLE:Collect Detailed Audit Logs CONTROL:v8 8.5 DESCRIPTION:Configure detailed audit logging for enterprise assets containing sensitive data. Include event source, date, username, timestamp, source addresses, destination addresses, and other useful elements that could assist in a forensic investigation.;TITLE:Enable Detailed Logging CONTROL:v7 6.3 DESCRIPTION:Enable system logging to include detailed information such as an event source, date, user, timestamp, source addresses, destination addresses, and other useful elements.; | L55: 8.5 | P55: X | Q55: X | R55: 6.3 | V55: X | W55: X | X55: https://learn.microsoft.com/en-us/azure/azure-monitor/essentials/diagnostic-settings:https://learn.microsoft.com/en-us/azure/azure-monitor/essentials/resource-manager-diagnostic-settings:https://learn.microsoft.com/en-us/security/benchmark/azure/mcsb-logging-threat-detection#lt-3-enable-logging-for-security-investigation:https://learn.microsoft.com/en-us/cli/azure/monitor/diagnostic-settings?view=azure-cli-latest:https://learn.microsoft.com/en-us/powershell/module/az.monitor/new-azsubscriptiondiagnosticsetting?view=azps-13.4.0 | Y55: When the diagnostic setting is created using Azure Portal, by default no categories are selected.
A56: 6.1.1 | B56: 6.1.1.4 | C56: Ensure that logging for Azure Key Vault is 'Enabled' | D56: Automated | E56: Enable AuditEvent logging for key vault instances to ensure interactions with key vaults are logged and available. | F56: Monitoring how and when key vaults are accessed, and by whom, enables an audit trail of interactions with confidential information, keys, and certificates managed by Azure Key Vault. Enabling logging for Key Vault saves information in a user provided destination of either an Azure storage account or Log Analytics workspace. The same destination can be used for collecting logs for multiple Key Vaults. | H56: **Remediate from Azure Portal** 1. Go to `Key vaults`. 2. Select a Key vault. 3. Under `Monitoring`, select `Diagnostic settings`. 4. Click `Edit setting` to update an existing diagnostic setting, or `Add diagnostic setting` to create a new one. 5. If creating a new diagnostic setting, provide a name. 6. Configure an appropriate destination. 7. Under `Category groups`, check `audit` and `allLogs`. 8. Click `Save`. **Remediate from Azure CLI** To update an existing `Diagnostic Settings` ``` az monitor diagnostic-settings update --name "<diagnostic_setting_name>" --resource <key_vault_id> ``` To create a new `Diagnostic Settings` ``` az monitor diagnostic-settings create --name "<diagnostic_setting_name>" --resource <key_vault_id> --logs "[{category:audit,enabled:true},{category:allLogs,enabled:true}]" --metrics "[{category:AllMetrics,enabled:true}]" <[--event-hub <event_hub_ID> --event-hub-rule <event_hub_auth_rule_ID> | --storage-account <storage_account_ID> |--workspace <log_analytics_workspace_ID> | --marketplace-partner-id <solution_resource_ID>]> ``` **Remediate from PowerShell** Create the `Log` settings object ``` $logSettings = @() $logSettings += New-AzDiagnosticSettingLogSettingsObject -Enabled $true -Category audit $logSettings += New-AzDiagnosticSettingLogSettingsObject -Enabled $true -Category allLogs ``` Create the `Metric` settings object ``` $metricSettings = @() $metricSettings += New-AzDiagnosticSettingMetricSettingsObject -Enabled $true -Category AllMetrics ``` Create the `Diagnostic Settings` for each `Key Vault` ``` New-AzDiagnosticSetting -Name "<diagnostic_setting_name>" -ResourceId <key_vault_id> -Log $logSettings -Metric $metricSettings [-StorageAccountId <storage_account_ID> | -EventHubName <event_hub_name> -EventHubAuthorizationRuleId <event_hub_auth_rule_ID> | -WorkSpaceId <log analytics workspace ID> | -MarketPlacePartnerId <full resource ID for third-party solution>] ``` | I56: **Audit from Azure Portal** 1. Go to `Key vaults`. 1. For each Key vault, under `Monitoring`, go to `Diagnostic settings`. 1. Click `Edit setting` next to a diagnostic setting. 1. Ensure that a destination is configured. 1. Under `Category groups`, ensure that `audit` and `allLogs` are checked. **Audit from Azure CLI** List all key vaults ``` az keyvault list ``` For each keyvault `id` ``` az monitor diagnostic-settings list --resource <id> ``` Ensure that `storageAccountId` reflects your desired destination and that `categoryGroup` and `enabled` are set as follows in the sample outputs below. ``` "logs": [ { "categoryGroup": "audit", "enabled": true, }, { "categoryGroup": "allLogs", "enabled": true, } ``` **Audit from PowerShell** List the key vault(s) in the subscription ``` Get-AzKeyVault ``` For each key vault, run the following: ``` Get-AzDiagnosticSetting -ResourceId <key_vault_id> ``` Ensure that `StorageAccountId`, `ServiceBusRuleId`, `MarketplacePartnerId`, or `WorkspaceId` is set as appropriate. Also, ensure that `enabled` is set to `true`, and that `categoryGroup` reflects both `audit` and `allLogs` category groups. **Audit from Azure Policy** If referencing a digital copy of this Benchmark, clicking a Policy ID will open a link to the associated Policy definition in Azure. If referencing a printed copy, you can search Policy IDs from this URL: https://portal.azure.com/#view/Microsoft_Azure_Policy/PolicyMenuBlade/~/Definitions - **Policy ID:** [cf820ca0-f99e-4f3e-84fb-66e913812d21](https://portal.azure.com/#view/Microsoft_Azure_Policy/PolicyDetailBlade/definitionId/%2Fproviders%2FMicrosoft.Authorization%2FpolicyDefinitions%2Fcf820ca0-f99e-4f3e-84fb-66e913812d21) **- Name:** 'Resource logs in Key Vault should be enabled' | J56: **DEPRECATION WARNING** Retention rules for Key Vault logging is being migrated to Azure Storage Lifecycle Management. Retention rules should be set based on the needs of your organization and security or compliance frameworks. Please visit [https://learn.microsoft.com/en-us/azure/azure-monitor/essentials/migrate-to-azure-storage-lifecycle-policy?tabs=portal](https://learn.microsoft.com/en-us/azure/azure-monitor/essentials/migrate-to-azure-storage-lifecycle-policy?tabs=portal) for detail on migrating your retention rules. Microsoft has provided the following deprecation timeline: March 31, 2023 – The Diagnostic Settings Storage Retention feature will no longer be available to configure new retention rules for log data. This includes using the portal, CLI PowerShell, and ARM and Bicep templates. If you have configured retention settings, you'll still be able to see and change them in the portal. March 31, 2024 – You will no longer be able to use the API (CLI, Powershell, or templates), or Azure portal to configure retention setting unless you're changing them to 0. Existing retention rules will still be respected. September 30, 2025 – All retention functionality for the Diagnostic Settings Storage Retention feature will be disabled across all environments. | K56: TITLE:Collect Detailed Audit Logs CONTROL:v8 8.5 DESCRIPTION:Configure detailed audit logging for enterprise assets containing sensitive data. Include event source, date, username, timestamp, source addresses, destination addresses, and other useful elements that could assist in a forensic investigation.;TITLE:Enable Detailed Logging CONTROL:v7 6.3 DESCRIPTION:Enable system logging to include detailed information such as an event source, date, user, timestamp, source addresses, destination addresses, and other useful elements.; | L56: 8.5 | P56: X | Q56: X | R56: 6.3 | V56: X | W56: X | X56: https://learn.microsoft.com/en-us/azure/key-vault/general/howto-logging:https://learn.microsoft.com/en-us/security/benchmark/azure/mcsb-data-protection#dp-8-ensure-security-of-key-and-certificate-repository:https://learn.microsoft.com/en-us/security/benchmark/azure/mcsb-logging-threat-detection#lt-3-enable-logging-for-security-investigation | Y56: By default, Diagnostic AuditEvent logging is not enabled for Key Vault instances.
A57: 6.1.2 | C57: Monitoring using Activity Log Alerts | E57: The recommendations provided in this section are intended to provide entry-level alerting for crucial activities on a tenant account. These recommended activities **should** be tuned to your needs. By default, each of these Activity Log Alerts tends to guide the reader to alerting at the "Subscription-wide" level which will capture and alert on rules triggered by all resources and resource groups contained within a subscription. This is not an ideal rule set for Alerting within larger and more complex organizations. While this section provides recommendations for the creation of **Activity Log Alerts** specifically, Microsoft Azure supports four different types of alerts: - Metric Alerts - Log Alerts - Activity Log Alerts - Smart Detection Alerts All Azure services (Microsoft provided or otherwise) that can generate alerts are assigned a "Resource provider namespace" when they are registered in an Azure tenant. The recommendations in this section are in no way exhaustive of the plethora of available "Providers" or "Resource Types." The Resource Providers that are registered in your Azure Tenant can be located in your Subscription. Each registered Provider in your environment **may** have available "Conditions" to raise alerts via Activity Log Alerts. These providers should be considered for inclusion in Activity Log Alert rules of your own making. To view the registered resource providers in your Subscription(s), use this guide: - https://learn.microsoft.com/en-us/azure/azure-resource-manager/management/resource-providers-and-types If you wish to create custom alerting rules for Activity Log Alerts or other alert types, please refer to Microsoft documentation: - https://learn.microsoft.com/en-us/azure/azure-monitor/alerts/alerts-create-metric-alert-rule
A58: 6.1.2 | B58: 6.1.2.1 | C58: Ensure that Activity Log Alert exists for Create Policy Assignment | D58: Automated | E58: Create an activity log alert for the Create Policy Assignment event. | F58: Monitoring for create policy assignment events gives insight into changes done in "Azure policy - assignments" and can reduce the time it takes to detect unsolicited changes. | H58: **Remediate from Azure Portal** 1. Navigate to the `Monitor` blade. 1. Select `Alerts`. 1. Select `Create`. 1. Select `Alert rule`. 1. Choose a subscription. 1. Select `Apply`. 1. Select the `Condition` tab. 1. Click `See all signals`. 1. Select `Create policy assignment (Policy assignment)`. 1. Click `Apply`. 1. Select the `Actions` tab. 1. Click `Select action groups` to select an existing action group, or `Create action group` to create a new action group. 1. Follow the prompts to choose or create an action group. 1. Select the `Details` tab. 1. Select a `Resource group`, provide an `Alert rule name` and an optional `Alert rule description`. 1. Click `Review + create`. 1. Click `Create`. **Remediate from Azure CLI** ``` az monitor activity-log alert create --resource-group "<resource group name>" --condition category=Administrative and operationName=Microsoft.Authorization/policyAssignments/write> --scope "/subscriptions/<subscription ID>" --name "<activity log rule name>" --subscription <subscription ID> --action-group <action group ID> ``` **Remediate from PowerShell** Create the `conditions` object. ``` $conditions = @() $conditions += New-AzActivityLogAlertAlertRuleAnyOfOrLeafConditionObject -Equal Administrative -Field category $conditions += New-AzActivityLogAlertAlertRuleAnyOfOrLeafConditionObject -Equal Microsoft.Authorization/policyAssignments/write -Field operationName ``` Get the `Action Group` information and store it in a variable, then create a new `Action` object. ``` $actionGroup = Get-AzActionGroup -ResourceGroupName <resource group name> -Name <action group name> $actionObject = New-AzActivityLogAlertActionGroupObject -Id $actionGroup.Id ``` Create the `Scope` variable. ``` $scope = "/subscriptions/<subscription ID>" ``` Create the `Activity Log Alert Rule` for `Microsoft.Authorization/policyAssignments/write` ``` New-AzActivityLogAlert -Name "<activity alert rule name>" -ResourceGroupName "<resource group name>" -Condition $conditions -Scope $scope -Location global -Action $actionObject -Subscription <subscription ID> -Enabled $true ``` | I58: **Audit from Azure Portal** 1. Navigate to the `Monitor` blade. 1. Click on `Alerts`. 1. In the Alerts window, click on `Alert rules`. 1. Ensure an alert rule exists where the Condition column contains `Operation name=Microsoft.Authorization/policyAssignments/write`. 1. Click on the Alert `Name` associated with the previous step. 1. Ensure the `Condition` panel displays the text `Whenever the Activity Log has an event with Category='Administrative', Operation name='Create policy assignment'` and does not filter on `Level`, `Status` or `Caller`. 1. Ensure the `Actions` panel displays an Action group is assigned to notify the appropriate personnel in your organization. **Audit from Azure CLI** ``` az monitor activity-log alert list --subscription <subscription ID> --query "[].{Name:name,Enabled:enabled,Condition:condition.allOf,Actions:actions}" ``` Look for `Microsoft.Authorization/policyAssignments/write` in the output. If it's missing, generate a finding. **Audit from PowerShell** ``` Get-AzActivityLogAlert -SubscriptionId <subscription ID>|where-object {$_.ConditionAllOf.Equal -match "Microsoft.Authorization/policyAssignments/write"}|select-object Location,Name,Enabled,ResourceGroupName,ConditionAllOf ``` If the output is empty, an `alert rule` for `Create Policy Assignments` is not configured. **Audit from Azure Policy** If referencing a digital copy of this Benchmark, clicking a Policy ID will open a link to the associated Policy definition in Azure. If referencing a printed copy, you can search Policy IDs from this URL: https://portal.azure.com/#view/Microsoft_Azure_Policy/PolicyMenuBlade/~/Definitions - **Policy ID:** [c5447c04-a4d7-4ba8-a263-c9ee321a6858](https://portal.azure.com/#view/Microsoft_Azure_Policy/PolicyDetailBlade/definitionId/%2Fproviders%2FMicrosoft.Authorization%2FpolicyDefinitions%2Fc5447c04-a4d7-4ba8-a263-c9ee321a6858) **- Name:** 'An activity log alert should exist for specific Policy operations' | K58: TITLE:Collect Detailed Audit Logs CONTROL:v8 8.5 DESCRIPTION:Configure detailed audit logging for enterprise assets containing sensitive data. Include event source, date, username, timestamp, source addresses, destination addresses, and other useful elements that could assist in a forensic investigation.;TITLE:Enable Detailed Logging CONTROL:v7 6.3 DESCRIPTION:Enable system logging to include detailed information such as an event source, date, user, timestamp, source addresses, destination addresses, and other useful elements.; | L58: 8.5 | P58: X | Q58: X | R58: 6.3 | V58: X | W58: X | X58: https://azure.microsoft.com/en-us/updates?id=classic-alerting-monitoring-retirement:https://learn.microsoft.com/en-us/azure/azure-monitor/alerts/alerts-create-activity-log-alert-rule:https://learn.microsoft.com/en-us/rest/api/monitor/activity-log-alerts/create-or-update:https://learn.microsoft.com/en-us/rest/api/monitor/activity-log-alerts/list-by-subscription-id:https://learn.microsoft.com/en-us/security/benchmark/azure/mcsb-logging-threat-detection#lt-3-enable-logging-for-security-investigation:https://learn.microsoft.com/en-us/rest/api/policy/policy-assignments:https://learn.microsoft.com/en-us/azure/azure-monitor/alerts/alerts-create-log-alert-rule | Y58: By default, no monitoring alerts are created.
A59: 6.1.2 | B59: 6.1.2.2 | C59: Ensure that Activity Log Alert exists for Delete Policy Assignment | D59: Automated | E59: Create an activity log alert for the Delete Policy Assignment event. | F59: Monitoring for delete policy assignment events gives insight into changes done in "azure policy - assignments" and can reduce the time it takes to detect unsolicited changes. | H59: **Remediate from Azure Portal** 1. Navigate to the `Monitor` blade. 1. Select `Alerts`. 1. Select `Create`. 1. Select `Alert rule`. 1. Choose a subscription. 1. Select `Apply`. 1. Select the `Condition` tab. 1. Click `See all signals`. 1. Select `Delete policy assignment (Policy assignment)`. 1. Click `Apply`. 1. Select the `Actions` tab. 1. Click `Select action groups` to select an existing action group, or `Create action group` to create a new action group. 1. Follow the prompts to choose or create an action group. 1. Select the `Details` tab. 1. Select a `Resource group`, provide an `Alert rule name` and an optional `Alert rule description`. 1. Click `Review + create`. 1. Click `Create`. **Remediate from Azure CLI** ``` az monitor activity-log alert create --resource-group "<resource group name>" --condition category=Administrative and operationName=Microsoft.Authorization/policyAssignments/delete and level=<verbose | information | warning | error | critical> --scope "/subscriptions/<subscription ID>" --name "<activity log rule name>" --subscription <subscription id> --action-group <action group ID> ``` **Remediate from PowerShell** Create the conditions object ``` $conditions = @() $conditions += New-AzActivityLogAlertAlertRuleAnyOfOrLeafConditionObject -Equal Administrative -Field category $conditions += New-AzActivityLogAlertAlertRuleAnyOfOrLeafConditionObject -Equal Microsoft.Authorization/policyAssignments/delete -Field operationName $conditions += New-AzActivityLogAlertAlertRuleAnyOfOrLeafConditionObject -Equal Verbose -Field level ``` Retrieve the `Action Group` information and store in a variable, then create the `Action` object. ``` $actionGroup = Get-AzActionGroup -ResourceGroupName <resource group name> -Name <action group name> $actionObject = New-AzActivityLogAlertActionGroupObject -Id $actionGroup.Id ``` Create the `Scope` variable. ``` $scope = "/subscriptions/<subscription id>" ``` Create the `Activity Log Alert Rule` for `Microsoft.Authorization/policyAssignments/delete`. ``` New-AzActivityLogAlert -Name "<activity log alert rule name>" -ResourceGroupName "<resource group name>" -Condition $conditions -Scope $scope -Location global -Action $actionObject -Subscription <subscription ID> -Enabled $true ``` | I59: **Audit from Azure Portal** 1. Navigate to the `Monitor` blade. 1. Click on `Alerts`. 1. In the Alerts window, click on `Alert rules`. 1. Ensure an alert rule exists where the Condition column contains `Operation name=Microsoft.Authorization/policyAssignments/delete`. 1. Click on the Alert `Name` associated with the previous step. 1. Ensure the `Condition` panel displays the text `Whenever the Activity Log has an event with Category='Administrative', Operation name='Delete policy assignment'` and does not filter on `Level`, `Status` or `Caller`. 1. Ensure the `Actions` panel displays an Action group is assigned to notify the appropriate personnel in your organization. **Audit from Azure CLI** ``` az monitor activity-log alert list --subscription <subscription ID> --query "[].{Name:name,Enabled:enabled,Condition:condition.allOf,Actions:actions}" ``` Look for `Microsoft.Authorization/policyAssignments/delete` in the output **Audit from PowerShell** ``` Get-AzActivityLogAlert -SubscriptionId <subscription ID>|where-object {$_.ConditionAllOf.Equal -match "Microsoft.Authorization/policyAssignments/delete"}|select-object Location,Name,Enabled,ResourceGroupName,ConditionAllOf ``` **Audit from Azure Policy** If referencing a digital copy of this Benchmark, clicking a Policy ID will open a link to the associated Policy definition in Azure. If referencing a printed copy, you can search Policy IDs from this URL: https://portal.azure.com/#view/Microsoft_Azure_Policy/PolicyMenuBlade/~/Definitions - **Policy ID:** [c5447c04-a4d7-4ba8-a263-c9ee321a6858](https://portal.azure.com/#view/Microsoft_Azure_Policy/PolicyDetailBlade/definitionId/%2Fproviders%2FMicrosoft.Authorization%2FpolicyDefinitions%2Fc5447c04-a4d7-4ba8-a263-c9ee321a6858) **- Name:** 'An activity log alert should exist for specific Policy operations' | J59: This log alert also applies for Azure Blueprints. | K59: TITLE:Collect Detailed Audit Logs CONTROL:v8 8.5 DESCRIPTION:Configure detailed audit logging for enterprise assets containing sensitive data. Include event source, date, username, timestamp, source addresses, destination addresses, and other useful elements that could assist in a forensic investigation.;TITLE:Enable Detailed Logging CONTROL:v7 6.3 DESCRIPTION:Enable system logging to include detailed information such as an event source, date, user, timestamp, source addresses, destination addresses, and other useful elements.; | L59: 8.5 | P59: X | Q59: X | R59: 6.3 | V59: X | W59: X | X59: https://learn.microsoft.com/en-us/azure/azure-monitor/alerts/alerts-create-activity-log-alert-rule:https://learn.microsoft.com/en-us/rest/api/monitor/activity-log-alerts/create-or-update:https://learn.microsoft.com/en-us/rest/api/monitor/activity-log-alerts/list-by-subscription-id:https://learn.microsoft.com/en-us/security/benchmark/azure/mcsb-logging-threat-detection#lt-3-enable-logging-for-security-investigation:https://azure.microsoft.com/en-us/products/blueprints/ | Y59: By default, no monitoring alerts are created.
